{"paths":{"0":["audios/tsbtnClick",1],"1":["ballGame/balls/11",3],"2":["ballGame/balls/5",3],"3":["ballGame/images/levelsIndicator",3],"4":["ballGame/balls/4",3],"5":["ballGame/balls/10",3],"6":["ballGame/balls/6",3],"7":["ballGame/balls/9",3],"8":["ballGame/balls/3",3],"9":["ballGame/balls/2",3],"10":["ballGame/balls/7",3],"11":["ballGame/images/spaceDecor",3],"12":["ballGame/audios/ballWin",1],"13":["ballGame/audios/ballMerge",1],"14":["ballGame/balls/1",3],"15":["ballGame/balls/12",3],"16":["ballGame/balls/8",3],"17":["ballGame/audios/ballClickCup",1],"18":["TextAsset/Lv_831",0],"19":["TextAsset/Lv_313",0],"20":["TextAsset/Lv_602",0],"21":["TextAsset/Lv_521",0],"22":["TextAsset/Lv_737",0],"23":["TextAsset/Lv_617",0],"24":["TextAsset/Lv_512",0],"25":["TextAsset/Lv_291",0],"26":["TextAsset/Lv_570",0],"27":["TextAsset/Lv_375",0],"28":["TextAsset/Lv_234",0],"29":["TextAsset/Lv_410",0],"30":["TextAsset/Lv_607",0],"31":["TextAsset/Lv_25",0],"32":["TextAsset/Lv_462",0],"33":["TextAsset/Lv_153",0],"34":["TextAsset/Lv_28",0],"35":["TextAsset/Lv_413",0],"36":["TextAsset/Lv_412",0],"37":["TextAsset/Lv_870",0],"38":["TextAsset/Lv_837",0],"39":["TextAsset/Lv_35",0],"40":["TextAsset/Lv_147",0],"41":["TextAsset/Lv_414",0],"42":["TextAsset/Lv_74",0],"43":["TextAsset/Lv_203",0],"44":["TextAsset/Lv_94",0],"45":["TextAsset/Lv_127",0],"46":["TextAsset/Lv_89",0],"47":["TextAsset/Lv_173",0],"48":["TextAsset/Lv_244",0],"49":["TextAsset/Lv_30",0],"50":["TextAsset/Lv_18",0],"51":["TextAsset/Lv_819",0],"52":["TextAsset/Lv_985",0],"53":["TextAsset/Lv_828",0],"54":["TextAsset/Lv_350",0],"55":["TextAsset/Lv_684",0],"56":["TextAsset/Lv_988",0],"57":["TextAsset/Lv_810",0],"58":["TextAsset/Lv_785",0],"59":["TextAsset/Lv_231",0],"60":["TextAsset/Lv_771",0],"61":["TextAsset/Lv_999",0],"62":["TextAsset/Lv_218",0],"63":["TextAsset/Lv_597",0],"64":["TextAsset/Lv_151",0],"65":["TextAsset/Lv_883",0],"66":["TextAsset/Lv_549",0],"67":["TextAsset/Lv_359",0],"68":["TextAsset/Lv_87",0],"69":["TextAsset/Lv_534",0],"70":["TextAsset/Lv_476",0],"71":["TextAsset/Lv_962",0],"72":["TextAsset/Lv_770",0],"73":["TextAsset/Lv_959",0],"74":["TextAsset/Lv_694",0],"75":["TextAsset/Lv_495",0],"76":["TextAsset/Lv_11",0],"77":["TextAsset/Lv_532",0],"78":["TextAsset/Lv_177",0],"79":["TextAsset/Lv_1000",0],"80":["TextAsset/Lv_794",0],"81":["TextAsset/Lv_450",0],"82":["TextAsset/Lv_172",0],"83":["TextAsset/Lv_987",0],"84":["TextAsset/Lv_273",0],"85":["TextAsset/Lv_613",0],"86":["TextAsset/Lv_183",0],"87":["TextAsset/Lv_149",0],"88":["TextAsset/Lv_427",0],"89":["TextAsset/Lv_934",0],"90":["TextAsset/Lv_432",0],"91":["TextAsset/Lv_835",0],"92":["TextAsset/Lv_679",0],"93":["TextAsset/Lv_784",0],"94":["TextAsset/Lv_84",0],"95":["TextAsset/Lv_471",0],"96":["TextAsset/Lv_836",0],"97":["TextAsset/Lv_64",0],"98":["TextAsset/Lv_321",0],"99":["TextAsset/Lv_957",0],"100":["TextAsset/Lv_298",0],"101":["TextAsset/Lv_319",0],"102":["TextAsset/Lv_91",0],"103":["TextAsset/Lv_123",0],"104":["TextAsset/Lv_241",0],"105":["TextAsset/Lv_468",0],"106":["TextAsset/Lv_380",0],"107":["TextAsset/Lv_325",0],"108":["TextAsset/Lv_977",0],"109":["TextAsset/Lv_119",0],"110":["TextAsset/Lv_245",0],"111":["TextAsset/Lv_680",0],"112":["TextAsset/Lv_456",0],"113":["TextAsset/Lv_360",0],"114":["TextAsset/Lv_757",0],"115":["TextAsset/Lv_274",0],"116":["TextAsset/Lv_545",0],"117":["TextAsset/Lv_719",0],"118":["TextAsset/Lv_260",0],"119":["TextAsset/Lv_651",0],"120":["TextAsset/Lv_391",0],"121":["TextAsset/Lv_515",0],"122":["TextAsset/Lv_849",0],"123":["TextAsset/Lv_769",0],"124":["TextAsset/Lv_632",0],"125":["TextAsset/Lv_763",0],"126":["TextAsset/Lv_707",0],"127":["TextAsset/Lv_148",0],"128":["TextAsset/Lv_294",0],"129":["TextAsset/Lv_698",0],"130":["TextAsset/Lv_859",0],"131":["TextAsset/Lv_73",0],"132":["TextAsset/Lv_809",0],"133":["TextAsset/Lv_170",0],"134":["TextAsset/Lv_330",0],"135":["TextAsset/Lv_39",0],"136":["TextAsset/Lv_116",0],"137":["TextAsset/Lv_271",0],"138":["TextAsset/Lv_194",0],"139":["TextAsset/Lv_818",0],"140":["TextAsset/Lv_254",0],"141":["TextAsset/Lv_578",0],"142":["TextAsset/Lv_184",0],"143":["TextAsset/Lv_52",0],"144":["TextAsset/Lv_625",0],"145":["TextAsset/Lv_946",0],"146":["TextAsset/Lv_736",0],"147":["ballGame/balls/8",2,1],"148":["TextAsset/Lv_990",0],"149":["TextAsset/Lv_431",0],"150":["TextAsset/Lv_438",0],"151":["TextAsset/Lv_590",0],"152":["TextAsset/Lv_618",0],"153":["TextAsset/Lv_36",0],"154":["TextAsset/Lv_712",0],"155":["TextAsset/Lv_266",0],"156":["TextAsset/Lv_282",0],"157":["TextAsset/Lv_12",0],"158":["TextAsset/Lv_833",0],"159":["TextAsset/Lv_163",0],"160":["TextAsset/Lv_665",0],"161":["TextAsset/Lv_227",0],"162":["TextAsset/Lv_900",0],"163":["TextAsset/Lv_68",0],"164":["TextAsset/Lv_754",0],"165":["TextAsset/Lv_798",0],"166":["TextAsset/Lv_29",0],"167":["TextAsset/Lv_275",0],"168":["TextAsset/Lv_199",0],"169":["TextAsset/Lv_382",0],"170":["TextAsset/Lv_92",0],"171":["TextAsset/Lv_921",0],"172":["TextAsset/Lv_299",0],"173":["TextAsset/Lv_787",0],"174":["TextAsset/Lv_19",0],"175":["TextAsset/Lv_5",0],"176":["TextAsset/Lv_232",0],"177":["TextAsset/Lv_971",0],"178":["TextAsset/Lv_691",0],"179":["TextAsset/Lv_576",0],"180":["TextAsset/Lv_933",0],"181":["TextAsset/Lv_389",0],"182":["TextAsset/Lv_415",0],"183":["TextAsset/Lv_943",0],"184":["TextAsset/Lv_182",0],"185":["TextAsset/Lv_192",0],"186":["TextAsset/Lv_997",0],"187":["TextAsset/Lv_309",0],"188":["TextAsset/Lv_333",0],"189":["TextAsset/Lv_782",0],"190":["TextAsset/Lv_522",0],"191":["TextAsset/Lv_518",0],"192":["TextAsset/Lv_901",0],"193":["TextAsset/Lv_678",0],"194":["TextAsset/Lv_318",0],"195":["TextAsset/Lv_386",0],"196":["TextAsset/Lv_390",0],"197":["TextAsset/Lv_443",0],"198":["TextAsset/Lv_297",0],"199":["TextAsset/Lv_727",0],"200":["TextAsset/Lv_33",0],"201":["TextAsset/Lv_139",0],"202":["TextAsset/Lv_723",0],"203":["TextAsset/Lv_489",0],"204":["TextAsset/Lv_117",0],"205":["TextAsset/Lv_323",0],"206":["TextAsset/Lv_98",0],"207":["TextAsset/Lv_486",0],"208":["TextAsset/Lv_580",0],"209":["TextAsset/Lv_31",0],"210":["TextAsset/Lv_331",0],"211":["TextAsset/Lv_491",0],"212":["TextAsset/Lv_296",0],"213":["TextAsset/Lv_649",0],"214":["ballGame/balls/2",2,1],"215":["TextAsset/Lv_762",0],"216":["TextAsset/Lv_947",0],"217":["TextAsset/Lv_919",0],"218":["TextAsset/Lv_258",0],"219":["TextAsset/Lv_504",0],"220":["TextAsset/Lv_461",0],"221":["TextAsset/Lv_242",0],"222":["TextAsset/Lv_526",0],"223":["TextAsset/Lv_452",0],"224":["TextAsset/Lv_434",0],"225":["TextAsset/Lv_834",0],"226":["TextAsset/Lv_334",0],"227":["TextAsset/Lv_93",0],"228":["TextAsset/Lv_791",0],"229":["TextAsset/Lv_840",0],"230":["TextAsset/Lv_974",0],"231":["TextAsset/Lv_677",0],"232":["TextAsset/Lv_667",0],"233":["TextAsset/Lv_760",0],"234":["TextAsset/Lv_306",0],"235":["TextAsset/Lv_513",0],"236":["TextAsset/Lv_130",0],"237":["TextAsset/Lv_96",0],"238":["TextAsset/Lv_252",0],"239":["TextAsset/Lv_955",0],"240":["TextAsset/Lv_773",0],"241":["TextAsset/Lv_749",0],"242":["TextAsset/Lv_357",0],"243":["TextAsset/Lv_211",0],"244":["TextAsset/Lv_891",0],"245":["TextAsset/Lv_713",0],"246":["TextAsset/Lv_114",0],"247":["ballGame/balls/3",2,1],"248":["TextAsset/Lv_56",0],"249":["TextAsset/Lv_503",0],"250":["TextAsset/Lv_862",0],"251":["TextAsset/Lv_169",0],"252":["TextAsset/Lv_666",0],"253":["TextAsset/Lv_726",0],"254":["TextAsset/Lv_494",0],"255":["TextAsset/Lv_687",0],"256":["TextAsset/Lv_161",0],"257":["TextAsset/Lv_755",0],"258":["TextAsset/Lv_768",0],"259":["TextAsset/Lv_210",0],"260":["TextAsset/Lv_739",0],"261":["TextAsset/Lv_529",0],"262":["TextAsset/Lv_262",0],"263":["TextAsset/Lv_928",0],"264":["TextAsset/Lv_514",0],"265":["TextAsset/Lv_815",0],"266":["TextAsset/Lv_20",0],"267":["TextAsset/Lv_593",0],"268":["TextAsset/Lv_734",0],"269":["ballGame/balls/1",2,1],"270":["TextAsset/Lv_102",0],"271":["TextAsset/Lv_445",0],"272":["TextAsset/Lv_814",0],"273":["TextAsset/Lv_701",0],"274":["TextAsset/Lv_575",0],"275":["TextAsset/Lv_510",0],"276":["TextAsset/Lv_162",0],"277":["TextAsset/Lv_403",0],"278":["TextAsset/Lv_395",0],"279":["TextAsset/Lv_361",0],"280":["TextAsset/Lv_709",0],"281":["TextAsset/Lv_644",0],"282":["TextAsset/Lv_781",0],"283":["TextAsset/Lv_622",0],"284":["TextAsset/Lv_720",0],"285":["TextAsset/Lv_802",0],"286":["TextAsset/Lv_2",0],"287":["TextAsset/Lv_383",0],"288":["TextAsset/Lv_601",0],"289":["TextAsset/Lv_213",0],"290":["TextAsset/Lv_879",0],"291":["TextAsset/Lv_507",0],"292":["TextAsset/Lv_557",0],"293":["TextAsset/Lv_912",0],"294":["TextAsset/Lv_179",0],"295":["TextAsset/Lv_237",0],"296":["TextAsset/Lv_952",0],"297":["TextAsset/Lv_261",0],"298":["TextAsset/Lv_341",0],"299":["TextAsset/Lv_79",0],"300":["TextAsset/Lv_342",0],"301":["TextAsset/Lv_742",0],"302":["TextAsset/Lv_730",0],"303":["TextAsset/Lv_758",0],"304":["TextAsset/Lv_212",0],"305":["TextAsset/Lv_131",0],"306":["TextAsset/Lv_355",0],"307":["TextAsset/Lv_904",0],"308":["TextAsset/Lv_982",0],"309":["TextAsset/Lv_738",0],"310":["TextAsset/Lv_663",0],"311":["TextAsset/Lv_62",0],"312":["TextAsset/Lv_588",0],"313":["TextAsset/Lv_673",0],"314":["TextAsset/Lv_897",0],"315":["TextAsset/Lv_639",0],"316":["TextAsset/Lv_407",0],"317":["TextAsset/Lv_408",0],"318":["TextAsset/Lv_930",0],"319":["TextAsset/Lv_384",0],"320":["TextAsset/Lv_702",0],"321":["TextAsset/Lv_228",0],"322":["TextAsset/Lv_76",0],"323":["TextAsset/Lv_132",0],"324":["TextAsset/Lv_535",0],"325":["TextAsset/Lv_250",0],"326":["TextAsset/Lv_208",0],"327":["TextAsset/Lv_496",0],"328":["TextAsset/Lv_88",0],"329":["TextAsset/Lv_4",0],"330":["TextAsset/Lv_498",0],"331":["TextAsset/Lv_829",0],"332":["TextAsset/Lv_416",0],"333":["TextAsset/Lv_402",0],"334":["TextAsset/Lv_393",0],"335":["TextAsset/Lv_995",0],"336":["TextAsset/Lv_101",0],"337":["TextAsset/Lv_604",0],"338":["TextAsset/Lv_838",0],"339":["TextAsset/Lv_81",0],"340":["TextAsset/Lv_453",0],"341":["TextAsset/Lv_568",0],"342":["TextAsset/Lv_683",0],"343":["TextAsset/Lv_264",0],"344":["TextAsset/Lv_887",0],"345":["TextAsset/Lv_519",0],"346":["TextAsset/Lv_661",0],"347":["TextAsset/Lv_993",0],"348":["TextAsset/Lv_940",0],"349":["TextAsset/Lv_918",0],"350":["TextAsset/Lv_66",0],"351":["TextAsset/Lv_236",0],"352":["TextAsset/Lv_129",0],"353":["TextAsset/Lv_581",0],"354":["TextAsset/Lv_140",0],"355":["ballGame/images/levelsIndicator",2,1],"356":["TextAsset/Lv_51",0],"357":["TextAsset/Lv_224",0],"358":["TextAsset/Lv_559",0],"359":["TextAsset/Lv_398",0],"360":["TextAsset/Lv_634",0],"361":["TextAsset/Lv_741",0],"362":["TextAsset/Lv_697",0],"363":["TextAsset/Lv_820",0],"364":["TextAsset/Lv_655",0],"365":["TextAsset/Lv_875",0],"366":["TextAsset/Lv_187",0],"367":["TextAsset/Lv_42",0],"368":["TextAsset/Lv_484",0],"369":["TextAsset/Lv_642",0],"370":["TextAsset/Lv_690",0],"371":["TextAsset/Lv_658",0],"372":["TextAsset/Lv_589",0],"373":["TextAsset/Lv_239",0],"374":["TextAsset/Lv_50",0],"375":["TextAsset/Lv_185",0],"376":["TextAsset/Lv_448",0],"377":["TextAsset/Lv_285",0],"378":["TextAsset/Lv_365",0],"379":["TextAsset/Lv_790",0],"380":["TextAsset/Lv_932",0],"381":["TextAsset/Lv_807",0],"382":["TextAsset/Lv_288",0],"383":["TextAsset/Lv_209",0],"384":["TextAsset/Lv_305",0],"385":["TextAsset/Lv_336",0],"386":["TextAsset/Lv_847",0],"387":["TextAsset/Lv_165",0],"388":["TextAsset/Lv_801",0],"389":["TextAsset/Lv_437",0],"390":["TextAsset/Lv_428",0],"391":["TextAsset/Lv_126",0],"392":["TextAsset/Lv_520",0],"393":["TextAsset/Lv_748",0],"394":["TextAsset/Lv_446",0],"395":["TextAsset/Lv_922",0],"396":["TextAsset/Lv_136",0],"397":["TextAsset/Lv_186",0],"398":["TextAsset/Lv_343",0],"399":["TextAsset/Lv_881",0],"400":["TextAsset/Lv_55",0],"401":["TextAsset/Lv_230",0],"402":["TextAsset/Lv_501",0],"403":["TextAsset/Lv_60",0],"404":["TextAsset/Lv_872",0],"405":["TextAsset/Lv_506",0],"406":["TextAsset/Lv_903",0],"407":["TextAsset/Lv_858",0],"408":["TextAsset/Lv_246",0],"409":["TextAsset/Lv_998",0],"410":["TextAsset/Lv_682",0],"411":["TextAsset/Lv_795",0],"412":["TextAsset/Lv_34",0],"413":["TextAsset/Lv_351",0],"414":["TextAsset/Lv_681",0],"415":["TextAsset/Lv_983",0],"416":["ballGame/balls/9",2,1],"417":["TextAsset/Lv_455",0],"418":["TextAsset/Lv_500",0],"419":["TextAsset/Lv_910",0],"420":["TextAsset/Lv_669",0],"421":["TextAsset/Lv_370",0],"422":["TextAsset/Lv_104",0],"423":["TextAsset/Lv_145",0],"424":["TextAsset/Lv_493",0],"425":["TextAsset/Lv_629",0],"426":["TextAsset/Lv_436",0],"427":["TextAsset/Lv_10",0],"428":["TextAsset/Lv_856",0],"429":["TextAsset/Lv_379",0],"430":["TextAsset/Lv_880",0],"431":["TextAsset/Lv_911",0],"432":["TextAsset/Lv_9",0],"433":["TextAsset/Lv_722",0],"434":["TextAsset/Lv_311",0],"435":["TextAsset/Lv_596",0],"436":["TextAsset/Lv_566",0],"437":["TextAsset/Lv_646",0],"438":["TextAsset/Lv_776",0],"439":["TextAsset/Lv_551",0],"440":["TextAsset/Lv_654",0],"441":["TextAsset/Lv_108",0],"442":["TextAsset/Lv_824",0],"443":["TextAsset/Lv_765",0],"444":["TextAsset/Lv_648",0],"445":["TextAsset/Lv_890",0],"446":["TextAsset/Lv_774",0],"447":["TextAsset/Lv_329",0],"448":["TextAsset/Lv_939",0],"449":["TextAsset/Lv_854",0],"450":["TextAsset/Lv_65",0],"451":["TextAsset/Lv_144",0],"452":["TextAsset/Lv_752",0],"453":["TextAsset/Lv_906",0],"454":["TextAsset/Lv_307",0],"455":["TextAsset/Lv_320",0],"456":["TextAsset/Lv_77",0],"457":["TextAsset/Lv_744",0],"458":["TextAsset/Lv_896",0],"459":["TextAsset/Lv_923",0],"460":["TextAsset/Lv_811",0],"461":["TextAsset/Lv_480",0],"462":["TextAsset/Lv_843",0],"463":["TextAsset/Lv_300",0],"464":["TextAsset/Lv_279",0],"465":["TextAsset/Lv_732",0],"466":["TextAsset/Lv_301",0],"467":["TextAsset/Lv_550",0],"468":["TextAsset/Lv_638",0],"469":["TextAsset/Lv_317",0],"470":["TextAsset/Lv_44",0],"471":["TextAsset/Lv_830",0],"472":["TextAsset/Lv_692",0],"473":["TextAsset/Lv_394",0],"474":["TextAsset/Lv_852",0],"475":["TextAsset/Lv_915",0],"476":["TextAsset/Lv_124",0],"477":["TextAsset/Lv_85",0],"478":["TextAsset/Lv_191",0],"479":["TextAsset/Lv_664",0],"480":["TextAsset/Lv_464",0],"481":["TextAsset/Lv_268",0],"482":["TextAsset/Lv_556",0],"483":["TextAsset/Lv_905",0],"484":["ballGame/balls/5",2,1],"485":["TextAsset/Lv_399",0],"486":["TextAsset/Lv_848",0],"487":["TextAsset/Lv_714",0],"488":["TextAsset/Lv_543",0],"489":["TextAsset/Lv_54",0],"490":["TextAsset/Lv_466",0],"491":["TextAsset/Lv_624",0],"492":["TextAsset/Lv_735",0],"493":["TextAsset/Lv_994",0],"494":["TextAsset/Lv_358",0],"495":["TextAsset/Lv_908",0],"496":["TextAsset/Lv_914",0],"497":["TextAsset/Lv_338",0],"498":["TextAsset/Lv_61",0],"499":["TextAsset/Lv_600",0],"500":["TextAsset/Lv_49",0],"501":["TextAsset/Lv_46",0],"502":["TextAsset/Lv_594",0],"503":["TextAsset/Lv_143",0],"504":["TextAsset/Lv_349",0],"505":["TextAsset/Lv_924",0],"506":["TextAsset/Lv_592",0],"507":["TextAsset/Lv_517",0],"508":["TextAsset/Lv_335",0],"509":["TextAsset/Lv_920",0],"510":["TextAsset/Lv_827",0],"511":["TextAsset/Lv_138",0],"512":["TextAsset/Lv_460",0],"513":["TextAsset/Lv_356",0],"514":["TextAsset/Lv_647",0],"515":["TextAsset/Lv_611",0],"516":["TextAsset/Lv_537",0],"517":["TextAsset/Lv_951",0],"518":["TextAsset/Lv_327",0],"519":["TextAsset/Lv_892",0],"520":["TextAsset/Lv_766",0],"521":["TextAsset/Lv_970",0],"522":["TextAsset/Lv_699",0],"523":["TextAsset/Lv_157",0],"524":["TextAsset/Lv_853",0],"525":["TextAsset/Lv_363",0],"526":["TextAsset/Lv_577",0],"527":["TextAsset/Lv_253",0],"528":["TextAsset/Lv_248",0],"529":["TextAsset/Lv_729",0],"530":["TextAsset/Lv_238",0],"531":["TextAsset/Lv_761",0],"532":["TextAsset/Lv_121",0],"533":["TextAsset/Lv_867",0],"534":["TextAsset/Lv_772",0],"535":["TextAsset/Lv_315",0],"536":["TextAsset/Lv_381",0],"537":["TextAsset/Lv_799",0],"538":["TextAsset/Lv_967",0],"539":["TextAsset/Lv_585",0],"540":["TextAsset/Lv_86",0],"541":["TextAsset/Lv_569",0],"542":["TextAsset/Lv_167",0],"543":["TextAsset/Lv_396",0],"544":["TextAsset/Lv_562",0],"545":["TextAsset/Lv_886",0],"546":["TextAsset/Lv_158",0],"547":["TextAsset/Lv_531",0],"548":["TextAsset/Lv_348",0],"549":["TextAsset/Lv_38",0],"550":["TextAsset/Lv_721",0],"551":["TextAsset/Lv_41",0],"552":["TextAsset/Lv_874",0],"553":["TextAsset/Lv_71",0],"554":["TextAsset/Lv_950",0],"555":["TextAsset/Lv_478",0],"556":["TextAsset/Lv_388",0],"557":["TextAsset/Lv_164",0],"558":["TextAsset/Lv_841",0],"559":["TextAsset/Lv_913",0],"560":["TextAsset/Lv_693",0],"561":["ballGame/images/spaceDecor",2,1],"562":["TextAsset/Lv_240",0],"563":["TextAsset/Lv_937",0],"564":["TextAsset/Lv_587",0],"565":["TextAsset/Lv_214",0],"566":["TextAsset/Lv_276",0],"567":["TextAsset/Lv_483",0],"568":["TextAsset/Lv_953",0],"569":["TextAsset/Lv_499",0],"570":["TextAsset/Lv_645",0],"571":["TextAsset/Lv_304",0],"572":["TextAsset/Lv_196",0],"573":["TextAsset/Lv_780",0],"574":["TextAsset/Lv_295",0],"575":["TextAsset/Lv_278",0],"576":["TextAsset/Lv_885",0],"577":["TextAsset/Lv_188",0],"578":["TextAsset/Lv_996",0],"579":["TextAsset/Lv_479",0],"580":["TextAsset/Lv_941",0],"581":["TextAsset/Lv_477",0],"582":["TextAsset/Lv_527",0],"583":["TextAsset/Lv_235",0],"584":["TextAsset/Lv_451",0],"585":["TextAsset/Lv_544",0],"586":["TextAsset/Lv_345",0],"587":["TextAsset/Lv_555",0],"588":["TextAsset/Lv_107",0],"589":["TextAsset/Lv_929",0],"590":["TextAsset/Lv_99",0],"591":["TextAsset/Lv_641",0],"592":["TextAsset/Lv_470",0],"593":["TextAsset/Lv_927",0],"594":["TextAsset/Lv_808",0],"595":["TextAsset/Lv_58",0],"596":["TextAsset/Lv_267",0],"597":["TextAsset/Lv_700",0],"598":["TextAsset/Lv_616",0],"599":["TextAsset/Lv_166",0],"600":["TextAsset/Lv_917",0],"601":["TextAsset/Lv_118",0],"602":["TextAsset/Lv_146",0],"603":["TextAsset/Lv_821",0],"604":["TextAsset/Lv_95",0],"605":["TextAsset/Lv_703",0],"606":["TextAsset/Lv_502",0],"607":["TextAsset/Lv_367",0],"608":["TextAsset/Lv_826",0],"609":["ballGame/balls/7",2,1],"610":["TextAsset/Lv_120",0],"611":["TextAsset/Lv_750",0],"612":["TextAsset/Lv_728",0],"613":["TextAsset/Lv_481",0],"614":["TextAsset/Lv_753",0],"615":["TextAsset/Lv_17",0],"616":["TextAsset/Lv_3",0],"617":["TextAsset/Lv_944",0],"618":["TextAsset/Lv_708",0],"619":["TextAsset/Lv_583",0],"620":["TextAsset/Lv_696",0],"621":["TextAsset/Lv_796",0],"622":["TextAsset/Lv_377",0],"623":["TextAsset/Lv_806",0],"624":["TextAsset/Lv_316",0],"625":["TextAsset/Lv_23",0],"626":["TextAsset/Lv_978",0],"627":["TextAsset/Lv_516",0],"628":["TextAsset/Lv_314",0],"629":["TextAsset/Lv_243",0],"630":["TextAsset/Lv_767",0],"631":["TextAsset/Lv_284",0],"632":["TextAsset/Lv_106",0],"633":["TextAsset/Lv_779",0],"634":["TextAsset/Lv_372",0],"635":["TextAsset/Lv_222",0],"636":["TextAsset/Lv_473",0],"637":["TextAsset/Lv_487",0],"638":["TextAsset/Lv_949",0],"639":["TextAsset/Lv_472",0],"640":["TextAsset/Lv_961",0],"641":["TextAsset/Lv_490",0],"642":["TextAsset/Lv_122",0],"643":["TextAsset/Lv_523",0],"644":["TextAsset/Lv_141",0],"645":["TextAsset/Lv_975",0],"646":["TextAsset/Lv_851",0],"647":["TextAsset/Lv_805",0],"648":["TextAsset/Lv_716",0],"649":["TextAsset/Lv_598",0],"650":["TextAsset/Lv_421",0],"651":["TextAsset/Lv_724",0],"652":["TextAsset/Lv_111",0],"653":["TextAsset/Lv_540",0],"654":["TextAsset/Lv_553",0],"655":["TextAsset/Lv_898",0],"656":["TextAsset/Lv_878",0],"657":["TextAsset/Lv_931",0],"658":["TextAsset/Lv_174",0],"659":["TextAsset/Lv_579",0],"660":["TextAsset/Lv_965",0],"661":["TextAsset/Lv_75",0],"662":["TextAsset/Lv_528",0],"663":["TextAsset/Lv_909",0],"664":["TextAsset/Lv_869",0],"665":["TextAsset/Lv_115",0],"666":["TextAsset/Lv_986",0],"667":["TextAsset/Lv_623",0],"668":["TextAsset/Lv_265",0],"669":["TextAsset/Lv_150",0],"670":["TextAsset/Lv_353",0],"671":["TextAsset/Lv_960",0],"672":["TextAsset/Lv_942",0],"673":["TextAsset/Lv_966",0],"674":["TextAsset/Lv_406",0],"675":["TextAsset/Lv_964",0],"676":["TextAsset/Lv_628",0],"677":["TextAsset/Lv_430",0],"678":["TextAsset/Lv_777",0],"679":["TextAsset/Lv_465",0],"680":["TextAsset/Lv_554",0],"681":["TextAsset/Lv_695",0],"682":["TextAsset/Lv_226",0],"683":["TextAsset/Lv_405",0],"684":["TextAsset/Lv_864",0],"685":["TextAsset/Lv_69",0],"686":["TextAsset/Lv_475",0],"687":["TextAsset/Lv_945",0],"688":["TextAsset/Lv_247",0],"689":["TextAsset/Lv_113",0],"690":["TextAsset/Lv_440",0],"691":["TextAsset/Lv_688",0],"692":["TextAsset/Lv_662",0],"693":["TextAsset/Lv_27",0],"694":["TextAsset/Lv_539",0],"695":["TextAsset/Lv_751",0],"696":["TextAsset/Lv_190",0],"697":["TextAsset/Lv_619",0],"698":["TextAsset/Lv_324",0],"699":["TextAsset/Lv_83",0],"700":["TextAsset/Lv_789",0],"701":["TextAsset/Lv_533",0],"702":["TextAsset/Lv_63",0],"703":["TextAsset/Lv_969",0],"704":["TextAsset/Lv_72",0],"705":["TextAsset/Lv_302",0],"706":["TextAsset/Lv_552",0],"707":["TextAsset/Lv_366",0],"708":["TextAsset/Lv_198",0],"709":["TextAsset/Lv_640",0],"710":["TextAsset/Lv_907",0],"711":["TextAsset/Lv_656",0],"712":["TextAsset/Lv_401",0],"713":["TextAsset/Lv_715",0],"714":["TextAsset/Lv_548",0],"715":["TextAsset/Lv_968",0],"716":["TextAsset/Lv_292",0],"717":["TextAsset/Lv_704",0],"718":["TextAsset/Lv_201",0],"719":["TextAsset/Lv_485",0],"720":["TextAsset/Lv_21",0],"721":["ballGame/balls/12",2,1],"722":["TextAsset/Lv_595",0],"723":["TextAsset/Lv_627",0],"724":["TextAsset/Lv_675",0],"725":["TextAsset/Lv_812",0],"726":["TextAsset/Lv_816",0],"727":["TextAsset/Lv_800",0],"728":["TextAsset/Lv_603",0],"729":["TextAsset/Lv_344",0],"730":["TextAsset/Lv_935",0],"731":["TextAsset/Lv_564",0],"732":["TextAsset/Lv_48",0],"733":["TextAsset/Lv_195",0],"734":["TextAsset/Lv_508",0],"735":["TextAsset/Lv_290",0],"736":["TextAsset/Lv_281",0],"737":["ballGame/balls/6",2,1],"738":["TextAsset/Lv_936",0],"739":["TextAsset/Lv_650",0],"740":["TextAsset/Lv_168",0],"741":["TextAsset/Lv_899",0],"742":["TextAsset/Lv_538",0],"743":["TextAsset/Lv_643",0],"744":["TextAsset/Lv_547",0],"745":["TextAsset/Lv_223",0],"746":["TextAsset/Lv_40",0],"747":["TextAsset/Lv_633",0],"748":["TextAsset/Lv_368",0],"749":["TextAsset/Lv_447",0],"750":["TextAsset/Lv_599",0],"751":["TextAsset/Lv_128",0],"752":["TextAsset/Lv_411",0],"753":["TextAsset/Lv_817",0],"754":["TextAsset/Lv_705",0],"755":["TextAsset/Lv_740",0],"756":["TextAsset/Lv_420",0],"757":["TextAsset/Lv_22",0],"758":["TextAsset/Lv_876",0],"759":["TextAsset/Lv_221",0],"760":["TextAsset/Lv_469",0],"761":["TextAsset/Lv_926",0],"762":["TextAsset/Lv_565",0],"763":["TextAsset/Lv_215",0],"764":["TextAsset/Lv_710",0],"765":["TextAsset/Lv_376",0],"766":["TextAsset/Lv_660",0],"767":["TextAsset/Lv_731",0],"768":["TextAsset/Lv_308",0],"769":["TextAsset/Lv_193",0],"770":["TextAsset/Lv_866",0],"771":["TextAsset/Lv_340",0],"772":["TextAsset/Lv_14",0],"773":["TextAsset/Lv_155",0],"774":["TextAsset/Lv_984",0],"775":["TextAsset/Lv_718",0],"776":["TextAsset/Lv_332",0],"777":["TextAsset/Lv_792",0],"778":["TextAsset/Lv_159",0],"779":["TextAsset/Lv_229",0],"780":["TextAsset/Lv_272",0],"781":["TextAsset/Lv_652",0],"782":["TextAsset/Lv_888",0],"783":["TextAsset/Lv_181",0],"784":["TextAsset/Lv_542",0],"785":["TextAsset/Lv_263",0],"786":["TextAsset/Lv_385",0],"787":["TextAsset/Lv_454",0],"788":["TextAsset/Lv_972",0],"789":["TextAsset/Lv_233",0],"790":["TextAsset/Lv_134",0],"791":["TextAsset/Lv_756",0],"792":["TextAsset/Lv_257",0],"793":["TextAsset/Lv_433",0],"794":["TextAsset/Lv_976",0],"795":["TextAsset/Lv_422",0],"796":["TextAsset/Lv_717",0],"797":["TextAsset/Lv_397",0],"798":["TextAsset/Lv_259",0],"799":["TextAsset/Lv_541",0],"800":["TextAsset/Lv_283",0],"801":["TextAsset/Lv_743",0],"802":["TextAsset/Lv_482",0],"803":["TextAsset/Lv_850",0],"804":["TextAsset/Lv_429",0],"805":["TextAsset/Lv_189",0],"806":["TextAsset/Lv_868",0],"807":["TextAsset/Lv_842",0],"808":["TextAsset/Lv_256",0],"809":["TextAsset/Lv_419",0],"810":["TextAsset/Lv_605",0],"811":["TextAsset/Lv_197",0],"812":["TextAsset/Lv_902",0],"813":["TextAsset/Lv_220",0],"814":["TextAsset/Lv_364",0],"815":["TextAsset/Lv_759",0],"816":["TextAsset/Lv_444",0],"817":["TextAsset/Lv_839",0],"818":["TextAsset/Lv_560",0],"819":["TextAsset/Lv_200",0],"820":["TextAsset/Lv_636",0],"821":["TextAsset/Lv_219",0],"822":["TextAsset/Lv_670",0],"823":["TextAsset/Lv_992",0],"824":["TextAsset/Lv_612",0],"825":["TextAsset/Lv_441",0],"826":["TextAsset/Lv_497",0],"827":["TextAsset/Lv_764",0],"828":["TextAsset/Lv_217",0],"829":["TextAsset/Lv_832",0],"830":["TextAsset/Lv_269",0],"831":["TextAsset/Lv_614",0],"832":["TextAsset/Lv_293",0],"833":["TextAsset/Lv_591",0],"834":["TextAsset/Lv_747",0],"835":["TextAsset/Lv_991",0],"836":["TextAsset/Lv_310",0],"837":["TextAsset/Lv_745",0],"838":["TextAsset/Lv_725",0],"839":["TextAsset/Lv_615",0],"840":["TextAsset/Lv_536",0],"841":["TextAsset/Lv_877",0],"842":["TextAsset/Lv_133",0],"843":["TextAsset/Lv_609",0],"844":["TextAsset/Lv_865",0],"845":["TextAsset/Lv_392",0],"846":["TextAsset/Lv_206",0],"847":["TextAsset/Lv_277",0],"848":["TextAsset/Lv_524",0],"849":["TextAsset/Lv_404",0],"850":["TextAsset/Lv_857",0],"851":["TextAsset/Lv_711",0],"852":["TextAsset/Lv_270",0],"853":["TextAsset/Lv_492",0],"854":["TextAsset/Lv_746",0],"855":["TextAsset/Lv_418",0],"856":["TextAsset/Lv_373",0],"857":["TextAsset/Lv_563",0],"858":["TextAsset/Lv_135",0],"859":["TextAsset/Lv_474",0],"860":["TextAsset/Lv_312",0],"861":["TextAsset/Lv_668",0],"862":["TextAsset/Lv_125",0],"863":["TextAsset/Lv_80",0],"864":["TextAsset/Lv_417",0],"865":["TextAsset/Lv_439",0],"866":["TextAsset/Lv_178",0],"867":["TextAsset/Lv_426",0],"868":["TextAsset/Lv_505",0],"869":["TextAsset/Lv_788",0],"870":["TextAsset/Lv_97",0],"871":["TextAsset/Lv_337",0],"872":["TextAsset/Lv_813",0],"873":["TextAsset/Lv_152",0],"874":["TextAsset/Lv_105",0],"875":["TextAsset/Lv_103",0],"876":["TextAsset/Lv_289",0],"877":["TextAsset/Lv_689",0],"878":["TextAsset/Lv_958",0],"879":["TextAsset/Lv_511",0],"880":["TextAsset/Lv_635",0],"881":["TextAsset/Lv_82",0],"882":["TextAsset/Lv_458",0],"883":["TextAsset/Lv_442",0],"884":["TextAsset/Lv_1",0],"885":["TextAsset/Lv_160",0],"886":["TextAsset/Lv_989",0],"887":["TextAsset/Lv_322",0],"888":["TextAsset/Lv_889",0],"889":["TextAsset/Lv_109",0],"890":["TextAsset/Lv_823",0],"891":["TextAsset/Lv_608",0],"892":["TextAsset/Lv_676",0],"893":["TextAsset/Lv_672",0],"894":["TextAsset/Lv_110",0],"895":["TextAsset/Lv_32",0],"896":["TextAsset/Lv_637",0],"897":["TextAsset/Lv_53",0],"898":["TextAsset/Lv_895",0],"899":["TextAsset/Lv_326",0],"900":["TextAsset/Lv_871",0],"901":["TextAsset/Lv_43",0],"902":["TextAsset/Lv_251",0],"903":["TextAsset/Lv_620",0],"904":["TextAsset/Lv_387",0],"905":["TextAsset/Lv_631",0],"906":["TextAsset/Lv_860",0],"907":["TextAsset/Lv_733",0],"908":["TextAsset/Lv_882",0],"909":["TextAsset/Lv_873",0],"910":["TextAsset/Lv_70",0],"911":["TextAsset/Lv_584",0],"912":["TextAsset/Lv_674",0],"913":["TextAsset/Lv_467",0],"914":["TextAsset/Lv_449",0],"915":["TextAsset/Lv_457",0],"916":["TextAsset/Lv_286",0],"917":["TextAsset/Lv_845",0],"918":["TextAsset/Lv_925",0],"919":["ballGame/balls/10",2,1],"920":["TextAsset/Lv_67",0],"921":["TextAsset/Lv_400",0],"922":["TextAsset/Lv_803",0],"923":["TextAsset/Lv_657",0],"924":["TextAsset/Lv_653",0],"925":["TextAsset/Lv_57",0],"926":["TextAsset/Lv_225",0],"927":["TextAsset/Lv_573",0],"928":["TextAsset/Lv_249",0],"929":["TextAsset/Lv_793",0],"930":["TextAsset/Lv_24",0],"931":["TextAsset/Lv_156",0],"932":["TextAsset/Lv_26",0],"933":["TextAsset/Lv_202",0],"934":["TextAsset/Lv_626",0],"935":["TextAsset/Lv_463",0],"936":["TextAsset/Lv_37",0],"937":["TextAsset/Lv_846",0],"938":["TextAsset/Lv_509",0],"939":["TextAsset/Lv_844",0],"940":["TextAsset/Lv_352",0],"941":["TextAsset/Lv_861",0],"942":["ballGame/balls/4",2,1],"943":["TextAsset/Lv_354",0],"944":["TextAsset/Lv_171",0],"945":["TextAsset/Lv_488",0],"946":["TextAsset/Lv_100",0],"947":["TextAsset/Lv_346",0],"948":["TextAsset/Lv_571",0],"949":["TextAsset/Lv_424",0],"950":["TextAsset/Lv_112",0],"951":["TextAsset/Lv_884",0],"952":["TextAsset/Lv_459",0],"953":["TextAsset/Lv_425",0],"954":["TextAsset/Lv_435",0],"955":["TextAsset/Lv_369",0],"956":["TextAsset/Lv_706",0],"957":["TextAsset/Lv_606",0],"958":["TextAsset/Lv_287",0],"959":["TextAsset/Lv_659",0],"960":["TextAsset/Lv_610",0],"961":["TextAsset/Lv_180",0],"962":["TextAsset/Lv_142",0],"963":["TextAsset/Lv_778",0],"964":["TextAsset/Lv_13",0],"965":["TextAsset/Lv_328",0],"966":["TextAsset/Lv_8",0],"967":["TextAsset/Lv_685",0],"968":["TextAsset/Lv_775",0],"969":["TextAsset/Lv_686",0],"970":["TextAsset/Lv_558",0],"971":["TextAsset/Lv_347",0],"972":["TextAsset/Lv_825",0],"973":["TextAsset/Lv_423",0],"974":["TextAsset/Lv_45",0],"975":["TextAsset/Lv_948",0],"976":["TextAsset/Lv_574",0],"977":["TextAsset/Lv_6",0],"978":["TextAsset/Lv_963",0],"979":["TextAsset/Lv_582",0],"980":["TextAsset/Lv_981",0],"981":["TextAsset/Lv_954",0],"982":["TextAsset/Lv_15",0],"983":["TextAsset/Lv_630",0],"984":["TextAsset/Lv_804",0],"985":["TextAsset/Lv_822",0],"986":["TextAsset/Lv_137",0],"987":["TextAsset/Lv_204",0],"988":["TextAsset/Lv_973",0],"989":["TextAsset/Lv_175",0],"990":["TextAsset/Lv_855",0],"991":["TextAsset/Lv_894",0],"992":["ballGame/balls/11",2,1],"993":["TextAsset/Lv_561",0],"994":["TextAsset/Lv_621",0],"995":["TextAsset/Lv_530",0],"996":["TextAsset/Lv_59",0],"997":["TextAsset/Lv_938",0],"998":["TextAsset/Lv_863",0],"999":["TextAsset/Lv_797",0],"1000":["TextAsset/Lv_893",0],"1001":["TextAsset/Lv_374",0],"1002":["TextAsset/Lv_216",0],"1003":["TextAsset/Lv_572",0],"1004":["TextAsset/Lv_207",0],"1005":["TextAsset/Lv_956",0],"1006":["TextAsset/Lv_339",0],"1007":["TextAsset/Lv_979",0],"1008":["TextAsset/Lv_783",0],"1009":["TextAsset/Lv_205",0],"1010":["TextAsset/Lv_525",0],"1011":["TextAsset/Lv_567",0],"1012":["TextAsset/Lv_78",0],"1013":["TextAsset/Lv_90",0],"1014":["TextAsset/Lv_303",0],"1015":["TextAsset/Lv_546",0],"1016":["TextAsset/Lv_786",0],"1017":["TextAsset/Lv_362",0],"1018":["TextAsset/Lv_980",0],"1019":["TextAsset/Lv_371",0],"1020":["TextAsset/Lv_47",0],"1021":["TextAsset/Lv_154",0],"1022":["TextAsset/Lv_176",0],"1023":["TextAsset/Lv_280",0],"1024":["TextAsset/Lv_409",0],"1025":["TextAsset/Lv_378",0],"1026":["TextAsset/Lv_255",0],"1027":["TextAsset/Lv_916",0],"1028":["TextAsset/Lv_16",0],"1029":["TextAsset/Lv_586",0],"1030":["TextAsset/Lv_7",0],"1031":["TextAsset/Lv_671",0]},"types":["cc.JsonAsset","cc.AudioClip","cc.SpriteFrame","cc.Texture2D"],"uuids":["0c/KfFpnNPsLvFaUHOa7qG","1fsUIncGtKjqCO9IaEpXbo","31/89nNP1L27N4PK6c8Y5f","5bfKNNx5BEg4SAD/wGWfS+","6ar8993v9A158YxFnKf6Hi","6c1yWhYxhJcaWI47/R7hXk","73zGpbPqNB9aUKwzoI4uuE","80N5Abl/JLqJZDa5knAMr0","81MHdB7lJK/o3V3uiqJxqg","8cS0TSq+lAU4ZFjRr9OsAS","8dg207YrdBva+I66npa2MS","c8uoxPJGpER6nr2ZaxSXPY","cckYIZNPVHXqwY+t7w7JL/","d7CPDd3R9JPrlY72LIYaGU","daZxDPMuZBMZKDVuT4tNlR","da9GPoKW5Djb68eahx0Hym","f0IwHoFzZNIZdeQ4n7CKLs","f4FJ1rG/ZKzb07Qy0wZT/r","00KiTif8FAH6h5fn8EhTaX","00YXTeqVlAt6NhTs+ex8x9","00pqUn1a9Exoyad3kl1ECe","006wQ2TJVDALi4z6HmMzNo","01MpRcKMNFErEvmaZPi7bK","01/VUjiy9IN5k34F8/uQq0","02JbYC1l5FIaUKeLYPthUo","02uK8qoylBg4T3bjvGZ/zP","02ybg12g5KZJNouarDNYh0","03LEBRPilAYbxu3pV+zrG6","03Luyfb7BBxaoL3xT0UZcn","03ePg1rcdIm5nyzW4DJS+2","03i2pMhpVGiLwO/AHFsowB","04PS2jB7BA9r8bwN9qd7uK","043iVL8dVPQIe8oufjicjI","05lOpfpZhDkqYumhlZI2ve","05rdnVMCdDEphnKBi0ajhu","05x5koR+tFKY7z1zJ/RSSF","0566Zlip1DXazfUNjHmDfA","06HDT6I9hH+aMoDM7Sf8cF","06VUNedmhA2LO5M82FGipi","06xuu+8W9JfYBjAggD826M","07B2ZUQ7VFS6vzxfuivHAw","07az0kyNBERb6jECviPw2G","07m3luz4RF46WNdGpBQESD","07nzfRAypEMrsNd03jyNN2","07pRgQHWdElJZTAkgHSnfU","07tV309s5FXLp3pGHmcf+P","075Z+bWypE87CQYHfbrOLr","08FKuPoXVCdK7Abin7tgAI","08+LZImsxCsZdIIJ82DxeS","08/snH+2VFCaWFWnPwG091","09BpDNVgpBArv2W1P/VsGI","09Cq3nw91HabF2CV76MH9P","09St7vhKxCDLOYA02Tffc4","09mh5sVUpL4K/ZQBQi7FaD","0aCm3O9c1LzJrX3XWt5g2k","0aiPhgdNJDqYCNPEYO8kjS","0aqT3REl9Cv4529owU5rnt","0au8arnJxDcavBkeThkIFj","0a9jBXE/BEHY/C7CxAbUoS","0bRnCw4flPoZA3qN6+RL+G","0bdly2C/VApKr8UYfTHJ5P","0brgQAKy1FypHH0jTK41L3","0cBsPG6MBJwp5APqbhNsS8","0cZMgw5IJIMKQeHHUdWP3H","0ceaB8IzFLGIj4a/GYRIKJ","0csYe+sLBClZqvi/CYtkOQ","0ctHba8BVKjIeUk8EV9SDm","0dFU7oMHlDkKyjazIMkhr3","0dZmX06/ZJSpuG/yRBTWPe","0dexm0+INCv4uH3ZDNzWop","0dp1SCZT9PjZpKbD5Edx+x","0d/i7vb5NBBIcBYZdD1GR/","0eINBTCoZLw6bfD8znaR8x","0ezGlJ3wxA5IKL+IVr0sO/","0e9a3e7AxJqJlIcVOcmFdj","0fQPaB1qVFD6ptwdZypKE2","0fUHKZQ7pCBapSjhXr4qlx","0fUJvGNxFPY7H1gCHkHY1K","0fVmFKLZVOqLGpnniny/tk","0f7mahYQVCYZWtrx7GXtZ1","10qynl5qRGLY4vAa6QSzdM","10ynEvnhxOd5sPOSFzYUPO","10zov30M9APJBrvcfTFb+A","100iPtEOpIebRjGD9a+A6+","11KdCF3flMZqIJZxWiBWdq","11aE5wN2xJZJ48jH1vHSil","11rqsRpQ5C8K0Yyq6228ig","11tL9SSV5B26sNYtFT3I+A","12JeefQStJSp3/EwANiBEV","12UDZHZBtF/YL7jE7Cgsr2","12YUDyBONLh71Xosryj7ld","121t3s3TFFlYdboEhiz836","123aPqYEpO/aNyqEHCRsyV","13cTwKX8pHQ4wLkunnMbCm","13ccV0FlpHXI+fW7bpiF70","13vhZCqQBB/ZE1NYJw63Mj","13xeYHoERCCYLFxvwiukdX","134pa3FeFNS707elYEzMi1","14GLjxQUtLbqzn8n/RwT+A","14GldrDYJGdbU1p04rGk0/","14R0iHl35DR4GGJvTqEGS5","14W367MMhPxoLb2QRwHOy4","14YB6QOg5K2qnWG4++VY1G","14lp8aaLZAU4+IcqaVsiNE","15JRenjq5MUo0eo7qyk1I3","15qpyKnd1LILP+pIstf0df","15tVx9v05KiqVkg/GT8BbR","15vZdaIA9CzozfrR2ANfPS","16JXn8gppIdpikUkYcVPj/","16LDImSjNLiKU0HsR/srPL","165c1BElZBK4eLGRH5/H2O","17DNb/DGxKZZsq8WYxu1XF","17TPUpLIFFU5oPgMUx59a3","17ecfQE3xBOrk6Y3RH3TJa","17mVGG6atFnY3Xij97JQni","17sKv3hmVBJ6J1FC7o0lGV","17wWENJf5Eor6jZt9SociG","17xjPjeilB/qtiTjZDQ6gw","18OBQ/zHpPmZRiOL5WREOH","18SsO0oCRFGbuIbPHd3eJH","18lIEYqSlGMr0eOWV/B0U6","18lg6sJeFAbricgGLPCkUP","18weP9CtRHg4jEiV025I3h","19KRoQJR1EHZ3CsApaoMjQ","195MB450ZAd7y2DuLqHLss","1auXBe4VxNw5SKzw+42lnk","1a/mkAMh5Lpo2JwooTnRUL","1benOuOiVL07O1OOlliKSX","1bn1lvAoJMmp0xWXT51WqV","1chzxwnOpHIJi6UJMGGNoY","1cj5w29KlHjJcmgCjgVUPx","1cuoemlIZB37voI0pAf3fL","1c+kg0+AlC2bkmNe0hsGJW","1dUP3BjNJDKYzGcyo4HTlR","1dVq+aIUVLG6Ekj8lT/LxC","1dke5JqAZBM4T3Po96ldcz","1eSK5x4UdOa4hcE7Osqsap","1el5Qq91dNsozbbSDt+YYi","1enR1m7RhJFIhvMqrwHXdv","1ettRqrZNCRrnPbswdFHIL","1ev6yQX+JFXKOVLlS9IeQS","1eyxvRv+RCLYHiMORElBsn","1e1g7pEVJNg5D7ZUe6n3c4","1e/1Xiq7hH3YFtr4T5ag1I","1fMCg+j+hKcqmtUn+EjFNT","1fXriWMExLtILsSC4b9oMS","1ft9yZnv9Jxrm8pF1xoVFX","1f2037nh5KUpsb7l8Hg9hS","20SBKh4mVEeq/fSpArN3Pt","21Fw0CySZIM4Xhxpx2l4N+","21MppRHJhIup1zfvkHngud","21QOvvXE5FsJOmwp6yFb7r","21RASGP0VBf7Bey2ZXeAW0","21ZYKHUM5DtKYI+osXLpg4","22SbvRf1RPhqHyd+f6QiFL","22obxYadZLfKqdy6ybImZ5","23+5OqI1hImKDytlqH1+An","24A0GtFeRL1a39DvDyTWdd","24eXulKRhI643yd8JJSKpd","24tlf4YqhPMLlhI0vy5KBB","241+WtyihGPI28y6HyyqI+","25MUkwtt9Cb6+NCG0It2Hv","25SRQHzfJJwrfrYPxNCX/W","25TD235eRLt4WMrqzfsUeO","25URdpIhNKMabk1RFt2axo","25lR7Vqs9IOYSTSPEYN+bR","25r8aXJHpGu6C6i3/VtiRQ","258vRWzPpMMrOxhDgky8xB","26P2KkbVxLZ56SojOrLpRl","26U1uOt7VNV5WMkGimQdk2","2637D/NldGY6+srzXkLh6B","27SsMa3tNMJJw0it7jpc+e","27Z8Fp6/tE0aDMl+4VA3uA","27hvOn8GNHW52MVjH6FGeI","271C+wGg9FLYnCOZnSNB9+","28CIeG3LhDB5oNZjeS4jjD","28YU3Yl+VKJ6c1bz9ggGLa","28cBrLEP9FrYUb8ZTt5SzC","2aNkC1byZHv5dp6jEqSB5o","2a9dz2PrdFg7AigBMwuX66","2a9u7aUe9OtLGimLr+oe7X","2bHR0R741PdKniHYlKgZ3v","2bn6cQh2dHpqIKSRur9E47","2buDnEtwlJs4DW1ElH5tOp","2buhJIpvdFJblGmAekJW6e","2bvjcEeCBElr1O8dFKMgN7","2cakkaimRIs5Z5+mD7eptO","2casXAIQVPn5/cxbL1VvzS","2cf9K78i1Gw5MhxliJlLgr","2cii1LHZJBX6l7H6DqGxD2","2cktuYJzlKYrEmvn9hJGZJ","2c0dZF5thPdYgrQ1+NKBlQ","2dZ5hJCUxBUIrh2rX0gsDw","2dx4x+4BhIFbLxDMRqX465","2d+96LupZMZpoGCPjU1CX/","2eAP7DxPBOG6FD4XLijsOV","2eNDUDFP5FR6B2npK1JPKR","2ewDbJyNRPI6CfSVy2/cvd","2e8bWtPUhIfI1wTV0PSFjJ","2ffvDhmNZFILeSFltCFcVe","2fzs0ZxSdCMbkG7ASerbNB","30E9WreK5FsJVHGRgEZw7g","30bwlZ3eZFBIZ+aIOD67lp","30fh7DHdlGMakSgYgLYm9e","30r89NEYhPZZqvUcfth+9N","30sEeLkaRMHIa8DzqsUO6U","31bv/zR9VLp48VlIX/V269","314QTrOGxIDoW9JrLk1VWC","32Dc1I5JVAS6FQQOjToRvn","32ffd7uapJapw6UHw1slNr","329Oe5KYhO/qtWwrNYWMkt","33HSSyBt9I6LdiTVnLfNU6","33Sq+rChRJr7Zy0cm3NeJP","33V4XDidJKOolKanfDjy20","33bCxwmrpIdJwMto+8bV42","33kJTCQfRNMoebm+tQ1Wli","34FDzJ/NFGmbaRnIOQzU9X","34IiEv5GtLCoBfR4heZ0lk","34agC2VM1OBaV6pZlLjPAe","348oFHh8dO6ILQ0+hY6Fdu","35CUr6GYdLsbhllBPP81am","35FXYxUehPGYEnNkpjb9Fm","35ahN2AJZK7rxcs0z97BMG","35qFPc4nZP245fa6dx1UXL","36FXKE/5NLOIIf+5HNAvY9","36FXRi9DZN44ORu9r2c9Jj","36Rg6INi9JIr7XRoiZRw2X","36R1NH81pK0bzze4mOY5n9","36jHGxtpRL+aaYd53qbfQK","36vLvXuTlAv5OJH+JQZ9Kt","37BnNfyxBNv4Kp6vKd+i1+","37PNHC06xINKsN3wP8QSVW","37aELTsfxOIYhdaKtF9ZJn","37bVT5ti5KLbSIcR+X3lFy","37/zlu/sRKYJthnqurVPjQ","38FntFvxZBGKf6/2wk7ONA","38LzhOyddNlq45s4o9waz6","38WhCYABFNW5XM0JufnC2P","38e/NRevxDCaTntlz2Ov9J","38pJmhqotDZ5AK3g+yRbK5","38+lpEeudMe7Gub3w8bkFV","39AMjkPbZG9atDFXY9E1rm","39UOkw3fBLP5UEhz8wdKvP","39U9CYeMFEs5tXiSxkk8Eb","3ardCKqP9A6IU4U4YJVaXk","3a0xn0kpRNAIgZ/ci8Suc+","3bIoCYYI1PeK6k/9GHeDFV","3bPJPMm01DtpPtaTT4DBx9","3biUh3xcNA4ZlKlmXVk+IY","3bipMVJVROtKYWHmfUsMWv","3btP3cpsVOVr98k6/OHvTT","3cJRTw6M1F2JuA1VYZIIJo","3c1etUzdNBsZ8EdKb9sBO7","3dCtxA7aBL17w+27HAVSTr","3dUwe3mhREdq0SH32loInM","3dVqEdlRpGVprjGPaByuxL","3dyTeTlGNAvrlyAgXEc8Ye","3eulE2ZdZKOb/FKbgJb6i6","3ez3KysOZHDLd07cmOcI+t","3e4OOEQrdJL6WO3u24uY9Q","3fZB53sidHaagZFHu4IAxx","3fe2+X2AJA9I10RYy8hYch","40Bc7evVRGmJCSWpUiueGs","40Cr6F9uNHU5yZd1ZZixVq","40GEiUzYlBUIKUYLBq6asV","40NQNOBaRDtblUD3Qrv0fK","40QDjUJpNHEJoNcqH7IRfW","40sNMQi8FKB52UOGL3ut5w","41p00nClhJ45sDrD/HoYH8","42buJmPhNESb1hyCp62UNu","42bwgldUtAjIwrKd+tfjuw","42vJUSdpFPsKYZXbfUX8zx","423kVQSvZCQK05QrbtY+/D","428UPB1ORMPbmkgTlAZV8Q","43HRgaX+1FH5tKIVdpFXki","43lQCT2eZLuLBpzzJ+XA85","43pk+bHqxGLazyKUXbd7/k","43xtUJeHpDAalIMt/J/h/S","435NtRu69DiK7GegwxIgbZ","44AclbQDVIW6gVIeWxmG3t","44MN5TRgRMm5oAdo0CeCXY","44PITW5dZO1Y2jyvnTpGsc","44V6TuE5hN+7ACDTRmURCW","44WXfSPd9ExKWLZICZbpIZ","44fAmyEmxAfKMn66jwMta0","44gtdYGBlOh5WsKICjii0Q","44r8p2Qt9Fi5JydY8xC1Gb","446sfcV1BP5rgfkbCMpppc","45BT0fNxNGE5RLS/H8uJqC","45H6OgMT9AepcGLUoX9t8E","457AG4TlRH7K110KGBkQk2","457Tmy4khFd5dFxCJS693f","46QyndFCBOjaSTqfe2POZS","46SrhagD5DhqOElCU8sCVN","46b0hGLGhLzoQu85OR2O//","46nXbwaVdHk7ryCaBes2ul","47Gy4Sl19JrIRZujEdb+pC","47b14rt+RKN5lXKmLHEf7x","47rGt8CZhFma7ZafrZnl20","47tqGpXqRIKrX8vI/CJR93","47yLkAFE5L0Lv7Rg/pdIgA","48HDEqa5tKwqhOolUbTsYT","48N/pv08dBV7kMi3ccSqJI","484CmVhuJBtrifxmVspwIw","485AFe64xHAr7t8jAVIy7z","49Vbjt6YBEGbBbDzY9g+SW","49YJHMclxJuKYQNAuEPwJi","49rLVHj+tKZIZ/RmnyDvnT","49+Ngd6IhMIqVOi+kaI3Sn","4apz9rldRHh7I8AWco7TgT","4bf6EHsYVKyrN6eh9Wdl1Z","4bjWpprX9M+5WzuJVrSx9a","4cH4XU8c5KYbOgmN/kaPzM","4cMsPk4ZlJUKwgqzlmehRM","4cVxb2trVPO5ZeDbExNuZI","4cgTgZn61G6KIUJ6moTPP7","4ckBNF989Dnr2JJ7TRkOgI","4cmDgrRlBK7LKA64emVCQt","4dhewgyllCH7bNeWKEF1eA","4dvRfNHVZKP6TnWXTVRevm","4dwsCjnM1BjZwIMJyUQgjS","4d50Ka8f9KAJLPY/1LP1C6","4eFrp9xRtPWIjU7TiI4XuD","4ecxPG9dlBs6UTXPnz+l2u","4ekTaFvrFHcLDHPyrwHumM","4e7wGy5XdJp5gCNEwwR9YN","4fsGJPcp5OCqGHyBpqbm2H","4f3C2N1ktE9oJ2DP26CT0z","502jy5k6tADazGZ2n1NCJa","51HDpEVs1P7J1GI55C+Jdy","51PQLsp0RF8KxktQfRjlL3","51ihiLVixItonXtAye1i87","51vhTnVCBOl7dXENOtcBH/","512tfISb9PzpKzLkWCxxoX","516ar73IRA9YBKQ0NiERHV","52MsEbSc1BIrVPkvNdPXwG","52iBHEIxlBhamRPO77MFH8","52pjQ8PCdN0bDftXszwaeE","52t8vItJFDGbxcL4C5n5V8","523f86PaZI44H6sMQNh1od","529BnWG6VFT7QAWIbMk8jQ","53B5v7qwxNv6MTUyCoofnI","53FjXmREBAaIddX4Fo6Zpp","53RYrP8mBKQI7J8LvsQYfy","53jPn2zSlBk6TVw0qnyr4o","53niEouGFO2o+cEYwv74EH","53+UzaVwZFP69mnx/UzXd9","54IW/K6rxJRr27yI78DQSi","54al2Mz9hHlb6YIk3ONXj/","54f8GdX41MzLCfOS6uKwld","54vTgH+J9BDKkgb7MOfYVY","541NuvsjZNXaHR1QXHl9bK","542rvNq8hMz7fXv/GyUOd2","55K3Doux9L94qadRo8GGlt","55La3sNnFDHo2d3LaCXosd","55WUwr2xlLlINWTJaHzbw7","55a7WgMX1HLqx3b7ftGYjS","55jICksplIaZvCY6ux0fjK","55yfBdQ5pAgJwpzTwnW62t","56iXZxtiFN4oU1w6AxWPNp","56khyW48RINKQNTpn3EH0q","56msmlmfZNs5aWihY+1EaD","566KSPOQZKwp1Wm+jv/lIK","57BajSDehG34rQyAR4w2Br","57K8mdl+dMhqgmGedtLus8","57Lcp+OcZLAaSVnnXqG+5L","57Yp7hA4tFCJ6AA381QiEV","57hgbdsS9A07RFWhjI1B2w","57icuXSBxJvrFrF0Zv3Io1","575qjCTbBDeaw9WIu2O+PV","58dTkQMH5ElaiTiNJOBpEg","58daho/ABHkZ5m5Et60+y9","59GRMVGipLo515WP2mwT2X","59IMVHjnBLD7DoJGq2i4Xh","59ajqFCSZNcLF2zlVQW/LM","59kwJ1+u1Lj411Ta1MdwdT","59nFAtfKhIQ42/Qgi1pyFM","59pOkaV5dBsp4tnibmAxou","59/s1JaI1NQJpCSRmhpL2L","5aUsPFqVdKRZbMxRf31wMV","5ag3ff8xVFjKuEU/rRnuFn","5a9HlvewtIuJSJfk1ApTpn","5bj13P/4RPsrpaDyPVzMox","5blLn8H4hI+ImgozbKPwEJ","5bp22XPSdJ85oWK1MbZDIy","5cfkrNdxVOeZ1Di7/mmtzX","5dDIDvGMNAsYahtwrNQqV8","5dIib2+dNP5YITNA28NuhZ","5dMoxjEQ5CVaaWEo7xrRTE","5ddlZnoNdDxqNxdjsXE4Jt","5d+eHC+AFL4JVRRnzM4RNR","5eMppDPiZOmoPEldpeqUM5","5eSAgfLWlNwbPddiDmdSaT","5epPLZRzFPUJI138Oanrnl","5e5SvLN/BGxIIdPEill5Ud","5e8KGmBnxE9qajMvp6isiC","5fBYfmU+BNd7xfGKweTL+Y","5fF6gdc51Pur12EBRCfQHv","5fJq5mV3lMn7vGMp0mFXOR","5fLZPTK9ZHsLqftf8m8Rh6","5fYWH0E+VHcYhEwKfutHSS","5fh1b1ddFAY4ez6NoW64Jh","5f08GIy5JI7ZfD54uwWHWz","5f8mb6zs9IrrR+bti4NZ84","60CkdIsCZNn6sOr2FaO+zf","60dsj0f59CvZpS0SRXT3yM","60vSHMO2lLJqyxLl65wP7L","61WhBvsYJFOYz6hWhKfY4M","61mRV7qj1KD4BrV3b/web7","61p9qX8r9HeKf0tjxtIJsY","62EWSb2VFK1pb9c0kYyg13","62VinLUopNtasJaVJRSh0K","621fxREcVH0pce34cFBV6T","627ZBNBrRLYK7/v6wbNHAE","63A81YWmlHoLfumK5SThNN","63S9LDH+hAg79jKhJu2vGq","63ikxzs9pPyrlLKcEBKArR","63suai4txB56G4Jy2vvScR","6301DN0eJN5pDEDGuHx1eX","64sVglJeRB0rKWADt9k4Fb","65Jru6XzlGeILQsAQQ4syM","65KusLfR5Fx4aGk5vnCFJk","65bykMp8tPz7rYtAD6mRrM","65chloNqRIV6wdI7bNGSJ+","66EtCpNeZLprniYMzTJ30K","66G7Auh3FI7qvyl4BHaZMf","66bNy7MndFkI88xoDWJTC9","66ks7dFOZExr1Tk+0wVveU","66yS5Og5JCWqwDQ5hx5jCh","661BMZod1KpYYOdQMt6Hrr","666Uz4ZvFPHJ5kBula4BCi","67XTDHyj5EF6uGYdBGScdA","67mcWwigFBT69+cScxg9Ax","67ykobCDZH6J+N1UJwc0lu","68DnjthP1GEbQKqoUZYwA1","68PRCSSHpAf5nC23nCfz6T","68Tbo3b+ZNOIP3pfKNLBrV","68rC7ms19EYIem+Sa9+kfa","68wREnMxRLKo3i1F45zfwK","68wS4I8rRIe5YthNcaN9Y6","68yucDOMNK44fG2dGQZYxL","684sateq9IC6HP9F2D5KQI","68+zkefApAE7KFPoSxqD3v","69CdKvE+BF0YKpmcg8sJFA","693FbgSlhBW6XWSZ/xPJsn","69/F1RJ1BJH6Z+RCo6equ9","6aaMmZLZJIUoA8hlYSJNwY","6ake/e2GdLXLOJuFsg+dVH","6a5klDMz9Ew6boaX17oDzG","6a6KT415xL16gylpe5W0aY","6a6NY4sxFFwbcY866jhodN","6a8qMcn3FEbpFEeprT3nyp","6bJwvjDG5BBY/O/38LBlbS","6bYFySp41GuoJCFP5UT5ar","6bat2Vu5NPeJq8OnKxx5G5","6btc92iltD77NMPEGu369E","6b/BUoszJBVKsO1tVLCbOd","6cIEVVx4ZLMLHH5Z5hFc20","6cIevNqPBLa4OPqh+ycG6b","6cg44eT8xAbIoLF4zVYZa0","6cmArn/l1IkKPwBT1PISG/","6coMi3OKVKPb4Ng9mgkzRB","6crz3yCYFEwZcc1NXu6dNH","6ct+k/vNtJFIxPd9W7Lyz2","6c5PRtxodKqbGjeUQeeGxt","6c+aCY4jdJg5k5I98xY8v1","6dXaIpgwpABZqBZSxKLpTY","6d0X6QDeRL24UbZ5l/zKoA","6eRq6sM7NCSriDnGEhBnYA","6eg4g2GfZEzak5XWS9Rx03","6ey4lh0cVBJaBEeg3FzqXt","6fDQSw9SRJBYqnAhcmelws","6fE5KDB3NDY5v+DfcQrzOS","6fgZYj0WtJkY0q6n9FxyZI","6f6As5Gx9OTJLLd85vDCeq","70LWiVd4lKlJlrakz9Ztnw","70Qk9xs9pMWoRseo1NIQLj","70iz1OZDBKfbxU9CtXztp5","701Oj7Y6xBwZ/AVuNX4vJn","71Da2+deRK/ZQgpOiNk7SN","71QyK9ltVLNrsTF7eq0U6F","71t+DEr75ApJV+mKQc2C8J","715HaA75lG1KOWzdicFOYy","72B53RZr1MC5yy9/+A3jKu","72Zx5ZW+tEEJnaMU0SZ8iV","72sGRY2gVOAqCsZcn8bNHq","72ufpjAEJEMIWMk5lPnViX","724DgX9N1HhK+M4XlzZKcG","73DEDAI4FETa/dEg6hnI+n","73E5yf6aVOEp8iRONkHJf6","73KCifr65P4J+2sigFhFd2","73+UgKPeNI1rK2yBH7g4l3","74JaPOWftPNoDqHFZJWWTL","74JpBOsKJFmKm7BPle63Mt","74uqEA++BGHY+pLgsIlE2Z","74zGsi//ZKOLvlibuGI/8M","75UwHlEOxAc534CPkv3w7s","75VC2nfMVA0o94VmQDZtZm","75bIuG71RF45n4Xj/SMzkm","75pjSLmr5PV7Jsz0TS8vkO","76UQtg1U5E4aYfuywCCFRP","76YyEk6GJIZ58fGJN8NXtg","76qetj/V5MD5m5Vc6yPDwU","76rFFn5A1Csp96+BeCRK1S","76t0LeGZlFXpCPXVULePIq","764pdyUNlNKLGi/MvfJzDO","77FdlcBvZOTqw7xWgPIP/t","77KuY68m5EVYZbWIXYUNth","77j/Wdmq1DC6nnEWLSoub4","77wJL/2i9J+KEj9xSgWhw1","775DEWFyNA8ZH2YXSwD0Qn","78H/ZfX6VCXaSFp/u1nODz","78IWkOf9lN+KXtVw+ClR34","78QYMsRbJDUY6KGDoYsAPm","78qtCXvJtO9YF8fMIyAnQJ","780qsGouhKi5ZPmCgK9Gis","781mhdMsJApaQPdUJQOrUS","79BP5S8J1Gvp22gfTX+lTh","79B5mUyLpL/ore2bJZGVBD","79VXD+3tZL96dHk46PLh+J","79eo3FrZ5GFINA1MKyP9ba","7bmDgCOEBLkqdGeDh9o02Q","7bqECDmgFH76fnmdySe0nD","7bs7N2jSNGJZeYJkoR/gC5","7b0zhYyd5BtIVPZPD07CPu","7b6dsXtx1B7I4xdcpUmwzK","7cTkSN4KRBXq/hR1RkVVY6","7cZHTrwo5NOJpBclEod8VY","7coIt1MmpJEYZiyAFFgK0W","7dC9y5AeZFX7PXsCSuT5Dg","7dibutaStM4oftehPqUtrb","7dqRbVGe5BJY185iBEHNCQ","7eMnG+21lBEYAEiOSHRceZ","7ebIDgSDFH3o1c4/U9LaQF","7e+LwvoiJJDYfm3C4tMSun","7fFSedVilCbIHZBOwyurok","80ANWI3ZZEma1wQ7Z0ju0B","80AWCTiHdJF4ALR8F08P/Y","80CPeq8iBCCbKuUQNPSHVW","80F6Ia79hAv4H8ZM1OzaZZ","80e5JLXE5O9br34bjMs0fP","80lcrlB9ZKjo93iT8TqRU1","80nwGNAU9OkqNKI//5mBja","80v8/+op1DxoLJCjf5ahef","81W++TWx9KOJiw8maC5u9j","81mz5BFV1A0qDncKwxH1Aq","82HupGuGZAq7Ud7ncCWQ+R","82NtmmxxVGKpkaMsSYZykS","82QgV2KTRLNpu9HPh2UKov","82qLWgy/hHZ4SU5mv8q5JG","82tfsPnq5EeLZyx6mSxVjd","8260sFezdMqL2asCEAKy1Q","83GeQZGT1EJ4xDeoVDSTuY","83G4+1zwBKNq7UOMbeNKgo","83THnJYQ9BzJjIVcnXfr8K","83eKMKEFtPzp5JXcDh9UBT","83oEnVd0lKu6HbJT1/sC1l","83qZiioMhO/bTNA7FQqZfA","839IhGDq5C9Z0Hr/iTJ74h","84T4QPoltJEphKxjSv9TLL","84Z7sQxGZEjLiR+9l3u6Ss","84fCuvR5ZNLazcpp1jWLf6","84hhkdZV5GVZGvGSoGHLS5","84mM0LEqxCyKRDR9YDj9qo","84vdlrKlxBTJ5WHk8mQ/xp","847a/0YI9CFrQIdFhjejcV","849bW3WGtJm6jrEREXHYfZ","849fl+/PlPeY/GW2t/SJLp","85CCSF0mpBf6fOvLHJErnt","85JV1OfFVIJb2yqFKCJ341","869yDLdeJFdbp9gTiA6Xv/","88f9rZM3lN2Zusg0HA6A/R","88jggOcc9FqbNIflIq6BZM","888yPP3tNLoJnyJlLNsBBw","89IJiKc+pNQbzjgYP3U7g0","89Td6AAcVNCI0hIKty9TbU","89WY7Yn61OgoqGvX6eEdK9","89YrG5KXxDTZzwXsREuCok","89jp1MyHlACZSr5N665wIv","89nKVxtppJD6BHtWWrPfPI","89xsUIifBPUYd/iubMtWzQ","893qpHAtVKbZ4Fj/lLz6Iy","8aK4fcr8FDWK+I5onTMFgG","8aPqP8yo5F15/Mf9qTzyM3","8aq2IzItlJH4oPFjJUJ4KS","8at2b6rC9Er6k4sR6g9aF9","8bLUwE7k5NKqqPW7Uv9LEz","8bPco7BA1CBaRKViY54Ng8","8b16Y5Ht9BCpRXAJ5RP3sC","8b3VE0RzVHq4iFGW9yHs+r","8cJoyc7qlLuIw1i2WFeO2D","8cJ7+QA29Cqa0fWqNs4zaj","8clzjWz4RJ3afZaooXFyvg","8csCNrakRJspVtLlDg0JMW","8c1uZ+gOJLsprwZafOSMQ5","8c4+Ye5StH07I/zKQrwF3s","8dJKHui7xNprgA/WkDn0rc","8d0ObYj/NGzqNzT3VKUjTh","8d4nyobr9F24jF7+YCV3ei","8eCAZuFNpFIoq3dpIw85/h","8eIWQE729A0ISpGEIVpAXd","8edZqNylVMuoPVuuFSd8KH","8eruofWf5InbYA3+HRabUV","8e3NMZoVBNWpnVcGpvhYzR","8fD/7pnqZLAaA3YxyT/ZBC","8fXtGFsbVJ1ofBNZJXBAC4","8fj9G7f41MLIcck6I19hXH","8ftSCvN+5CNbi7tjz8anFH","8fygZI1TlH5Kwb82kMVyth","8f2Pf/TVxF1bCOrC+zwpQX","90MSAF13dIkZcF59un2gOY","90ZpzQNZ5M24gN9zLUB8ZK","908xTmS2lDaKao1PUIlmLd","91Ex5HKjZDuKKNqicEJpka","91ltzWXnFPHK4qPN7HWsU6","91ygPHiPpP1rEyXzOn9NLH","91+XBbbZ1AXbfXCw+moFyp","92HYLdAEFPfIyrwkvTKYUT","92WuDvzx9AOrVxqFWZN4ec","92jo3qWUZHHqOCQOrUjNIJ","92ribGh2JJnIwwrumeC7b/","92tEbTTA9IF7ggelhjIelL","93CuPId0FHcJ4hmsfWmzII","93IIX4uThPUYTZTVnQZYQ2","93MoyG3j5L+6f9+xLqKyop","93W/CNSsZG3LnohQDzxq+I","93d0yoYQVJb5T02rpc80YN","93mnlScOFP8KXQvmAX3scr","93xDR3w5FLapDim7j3nPP7","934g98JzFMLZHnBQPryA8y","94Fm3H0KFJUr0jZ9cHCS5A","94K7NI1gJFW4GwXI2e4LwR","94hXa6+ApGsak29IBcZvn+","944jausnBJCIWfPnTplfvc","95YAS155FM/qM/rZUWiK2I","958klfQMxFboCtfsXOZ4Su","96IobXdKxATq4YqoVTG8Vt","96KENebXFJl7D6LA+j4/+K","96OqSpPqhL+KUz+ZvH0L7a","96hgmEFPFJ0LSelYYHrjy6","96664Ij8dCyaUePSxw80o0","97TrQ+iJZAIIYJ8ejpboRq","97kInrm/9K1oNUn5PGmm4E","97kLgxgQlOj6E2zP1Z9u5e","97pTcp5AJJ/pIA0Vrb+TpH","975wGjOclEe7AadmYifbBs","978Sxyw6xDDLqyIYnGh9xT","978m2PHXFPgI+z7qF/HoxA","98ARoTIyxI25rXMEaGIGxt","985dR6AKlO1L5VfqENq44f","99OY0kh+dKMbRmSUYctd+f","99Z3iVwRtD+4m+z+kopqAM","99mIVaJctNEp4ydIzppeJ3","9aEGQ6ZkhDO6rsrhXuasq6","9aPFYeg1hBtKCQLxZKywUv","9aVvkbpTBCBpccBJDyxFX8","9agVKIxkdEVIHrYv+g3qD0","9ajEpG8HlN56qnkdczFYGW","9apu/ZBmtE7ZxC3xiN4why","9bU6cztt1ADa++NhFCpxLf","9cGePnvUNBO4QxL1J8b6tt","9cNK3J3P5ABqtr6g6rxsLk","9ciz7sM+hOA7dHySum7Btg","9cwDpU8iBCFbcfoyMn5vUd","9c5XidBkNIRb0R4OdLE43r","9deV9RDC5PzJX36lxW/Tdg","9df+Bvj+BLp640Js+fLJw/","9dyivqbVtN8Iek69XbL2N+","9eLZrfgP9HcJN3dgtSKqkP","9eUkeCVkdMV6CLChb4kAcH","9excx2FqpIlqkD10g4DmL1","9e/4i9PLlEN4NfOpnMJ429","9fYLw/tTJLk6KUcObh7YYT","9f0Yk2wF1Ce5Nb2U1lVmw9","9f0smYiylK0a6u8m7HiBDo","a0HwpLKClERYb2NdVZ0d1b","a0TadQn3xJw6EGKBnLuC7E","a0bsVurFdKAY/WP1YWTAZb","a0p4Ab8RxEXJVFQDhIr7yU","a03XCi7QJBvprrWscsJhSb","a1MNMcRCRGiZPaHAl9VBPh","a1Tcm3NWpI97xskXMgKudL","a1Xj4pJ4FKXZ227G6pkX9j","a1vvuoFYZJf6Os6ahxENrl","a11uRSICpLrJ+EJrqm/FPI","a14XtYm6hA8btQMW810nJq","a2DkX29A5HiaKL+EBiPIyW","a2HmVTwqBFHojI+Ha9xNxU","a2K1mvk21NP5PdoUUmV3MH","a2S8IUCdhIcI0c4u5F+t0q","a2ofZt9g5Irb374lybBya3","a2yc0iHZFOnKv0+WdKEnAJ","a27mH3hadOp6iToNeKxHDO","a28hVQcINHu6Am5fSak8iR","a3LRUnCH9C4pbjU4XfYpk2","a3OkrK0wNCWosq02hF+497","a3Wlci66hPC4ePfACX3CA2","a3fVc+ujVA4ZV6NPp3Wtnm","a3muGcQBNBpJDNv3EUc3ht","a3nqJjGe9PU4xGxn0N6Wis","a3wUum9n9LPoDzfJUVwlkq","a35WOdAdlLur945t5m3VHW","a4GJhkfPRL37v9ZDTWVyWv","a4aYVHtqhHCZRS/ydwkndS","a4bqf2uDZFGrgZrrKtwSWc","a56fa2xeBBnac3I98FcAJh","a6Fjbt7klI+ZbaCIK7ZNla","a6KtJLIRlMxJvjut0976H7","a6fLAEuGtAgKwGQ4lTucYb","a6kaT9zH1HR4uPnuRK/pgA","a6nV7JZlJGVonmYBfiM5Nt","a6y/mlhJJHaqWVkQT7fR4J","a7Vn8WDPhNiaD6MsFR5IO6","a7rqo+M0xPYY0gIQw691U9","a7txfWjXxBWoMrJs4luf8c","a7u6Z19LlN77gPxLTMKN85","a74RnwYtZFLq5h+lqZ+oUW","a8LGSHlzBFtZhEz5v8sQTy","a8hIyP18ZPh6mPyS0hHKKh","a9b4VZ0gJDsrMyiI1z44EZ","a9j+jQIANKP7LsXWPq0nRV","a9152MVBRFvYmTqlKj6siq","a9300+mN9BU4i0lUgyFABm","a9/KyFnwZE/6aH4kSGNvbB","aaM9v8oklOS6l/TPXSoTDR","aaQr4BoXBKB7/v5kjz+ldQ","aabuolAuRKnpfQw5kQs8yQ","aab8ETc3JAyJ4+YbCc2Wk2","aa5I4FMc5H6InpSapjLkV3","aa/ycLkZ1FhpzMxOCe7lHE","abBNNj5epMBLsiOzgXnZXs","abL8LqJdtBNYB7an0fXSGi","abPjmFEuhHfJafszH4Km4n","abXE/46KZOwLmDj217ioep","acgKxlsuBKr795aUTiOzlb","ac3T5GwW9OAI8Xu/RA7a9N","ac6vL8w3FPooHEFf/JgP8q","ac9nGspaZKSaKUtxr8BKXQ","adk8G9mTlGB7UIcBSEzr+z","adqaIGBk9Ktq9zrphoByEd","aeIZhtrq9CGJIKF5nvhnDN","aelzAUxXNBd7RK+oCinUUO","ae9Orla7RE47Kl3LvK82Hk","afQ+bT4EdENrlV7grDn4Sh","afT41CwUZESb8iw1Ldv0Jm","afbD3ym1BO4Zelp1Sj29Ck","af/48Ypw5PUqSFIHNXzJOn","b0Ea6arypN2bEUQoDsSxQw","b0KD65D8hJwY3sQlOCi00q","b0uCDaLYJCSrVet2eUFncl","b0us61+dZGmogfqHOYl9Lu","b1DRhk8sJBGbU4BIl+UybQ","b1DrGAJqZEBYSac3vaWaMU","b1F0FTxQNMwrLygSR+/WkG","b1McZez3dCaaMlvf7b77qd","b1UoAox8xJop0gfaufRLYG","b1fvAAne5CLKk53L0LFOKJ","b19F4UC9NDxYpHZaNnuN4A","b2DOADD55G16IyXbOQEzHZ","b2jembadJFZZ9xVdV6QvuR","b2uykvfDhI/a+ACEpo9++A","b3MVRSdk9KOpMgKT7UaVGi","b3iDTwwIxBiIscg/dvkXjw","b3iogBPdhJ7KoXY36CsFkL","b35961iLlO94piC6sPabnq","b36KExI6JCspwnCCJGgOrb","b4UM0PwPVLNb/W1poU4p7C","b4g9vOMq5DWK4/tkgE2M3j","b4ulPHXLVPWrUaiYRo6nfm","b49rtPf0xO0LTJNNEbu6VQ","b5SBPqqUpJNYQtqT0iides","b5kKWvQ1ZA34sASiEPzpFt","b58Vk08UNKCbjbVLtDlzV4","b6G0vx1S5LDLCthhy/KWz1","b6HmrF+gRMOpLSDrN34dz0","b6PcK2BMtIoKdv69lvKp+N","b6wl1aNWdMHKbB6IVxd8R/","b7hyscIqJKFalf6qvtvKRa","b7weYJqYxFJpQJt01teuNe","b8CynDQrZAObdML3/BcFjf","b8xw66VlBCx7AZjGv2YMiB","b84WfJgMNM57+PHOMK+wGn","b84gQnQ/lGzo7ZjO9H9Pok","b85KiQ6C5EKJeH5lqTSLD9","b85L6pa0RLarheMg066rtn","b9C4eX4URFmbk8T1dfmVEl","b9L8Tj/1lIqpPa/IuFPUUw","b9drn0uBtCG6MlMIdjrTTK","b9gAHxbGdEDZ4Dn92BI5lf","b9wKPR1Y1Kg6tM+SVT9Rt8","b98MyDIZFM5LN2ObP94S/D","baNQ6o8HpA4pDpBkAS52Pd","baU0wwXwFL37l0rLTcBdNU","bayRMd8C1EUIcwXbiBxflj","ba16P4UMhLqbcBTfKeZJof","ba83H1LFJD5pH5VXH5e4hu","bblCVDIhtOpb2G+ZqrLD81","bcPxuIOIVBQaxdg22IF2TF","bcQml5bmRNGbQ7QsnJeqQI","bcau+DxldJa4eoTsA0EXgJ","bch9Ut82hMPLZAKiJwKouJ","bcm1MGOH5D9YPvWQXJ4Gvc","bdCDrO0aFDNJwoktExtZSP","bdFLozJqRBor8BfiLLmeI5","bdlpDEf0lKvb5XMbB1XN+r","bd7xSHLvVEC6+pIXDsSYHm","beCyylRk5GM50/EGWlQLfG","beEcK00GtBoKnUnmfKaqm7","bedp7KephGRJyMCAB3FpQS","besdvRY7tOfIvyWxirYGRa","bfL5d7PfxC+Z0SeMCGimX/","bfRrLG+c9GsZ6vx7LqpwKj","bfY9QZN9FAyas3scB+2oKe","bfaOfe07RCEKUjlM2wXnLQ","bfj2/+JOZMHrJbwoMdZvtk","bftqYIW4JA2LXqHeC9KNY4","bfxX5pEWpJX5I9xs+MtFfj","c0FgkaKQxCmLhD0MqIitBA","c0OfZfQl5GZLhB1N5bDcfv","c0idxiZaVOoLki7VIuBAnH","c0namn7Z5OzKxOExy0xyOG","c0p7vGrztCrKF31ifC1q9E","c0yHc1U4RK6ZkmGRiTvlPx","c1WEh1ypJLwYjexoxUMtmT","c1zspBe7pKsJT279DywmPp","c2AF4IvMdG/rvdjrx9yaRv","c2E53BAOhLB4PAOOJnLu1j","c2oilNuwtA/ZVI/L+LCPFT","c29qB0c/1NjIVGJ/DiWvH9","c3EbxlNVpIH6z2C0E7Q49p","c3LpjsNlRK1a5DJKPpCyjE","c308p+RIBJuKAAmzYr+qX2","c4HpB1qitMGLUjmW47Pruf","c4N414UHBMdo6B5QiQ0prN","c4SRr1Rz1Pt5HH7XI54bLl","c4bOYCdnxEbLTg4Ie3BVEu","c4n9COssNHy50vyCBSBBDv","c5viece05PhY/lQVVvhg4P","c6N0OWPORHOrVdDP5RnwhD","c6Tugk2xxM2buj3vNxZKEa","c67GGUNKlK0JxMzTitIydR","c694lJ8t5K6KJkGrwFVR8n","c7Ef/BaedL7aVF6iiYhY7+","c7SODBUyROH78j4Fis1/Sf","c7dh2hAYpN16zkF8ES2woJ","c7usSXYCBHI7OtuLkl7kES","c7wOXeVzBKWKUFAKb11Ww/","c8kTGzsUxNGZe+39Znrs5t","c8upBceQVLhLo+ImWKX85A","c86+3MDIJEM5db53e9VGew","c89WU86dtEPbbZ2Ay2wJoV","c9ahBWVRtFWoQ2bBVhb7kt","c9g0wjPcpAKJawCfAPCqGi","c946CasXVNN6GFb2TxkcMD","caKSiRyXNB/ZwKBD99hVi7","caSZGsolFMuomq+6Nm71lT","caVg3I1zlLdIX36lA7We4O","caXl5Fpo9BDJgpiMzQpgz9","caXysQICtNVoNewhztUtGL","caaup4DpNBr65GyVlqwDlb","calup3bx9K9qCiOkvZhF5N","cao8Va3ApIF5c+nl8jX0Fp","cbbvWvK8hH4pyib4B4hmnM","cbw6nEgLdFza22Tn0rjU0p","cb6SEPN2lPEal2YxFHhwqh","ccRszC0qNFO7iVu/R2hUG8","ccTwW6NIBL0ors0X291Po3","ccfDjr4W9KQarxdl7HYI8X","ccrtwk3xVAq7wsahJd+Vkl","cd2ZJE0cFPWZSZS0DezJr7","cd3Hqt8MNJ0aqz6aSDdIEP","ceBkWXtMJHn5T7XO5vjQ94","ceS9UIeIJDy4CRq9D1i/8f","ceeTYkezBLb5K7Wyuze2Lr","ce4EwTPJtGf6QTDjT57A9F","ce9/hB1XdPRIrQm4NeBT0l","cfI4vwnW1PFao88RytXTKi","cfPiQS6etPaK+Iri/EoGEV","cfa8Mdrf1MKr94qdwOBj/p","cfxsbCkoVASZpTTiUbvCRm","d0Bpmze1NLeZFuR2fEdWfS","d0NTugCExEgL772UOl8Hiz","d0QXN9uoNPHKc74cWthksZ","d0yCMknltAy7nk1cFtc7Ff","d014Yyl61Gx6oY3zL8/tc9","d16ONVBo5Hl6RLAxzyNX2H","d2Dco/+GtPsbUXGEmK6nX8","d3L76xaoNH5681xr2Z0/X4","d3cAkZsyRNZKRgGnyQAko6","d3f/gvGAZINIYbDuHFk3wc","d3yqGXQFpH2pHxUJSrnaEM","d33/9IH3dJDIu85P+SxrGK","d4YrGt2GJPvow50pRVEctt","d4bI8kAThNVohz676M9vZ7","d49MsFnh9FDZzxI7PDu6QB","d5OmfBHuFP8YyeCDVwBJQG","d5nITQiq1GN5KirS7MUCM9","d6J9oYn+ZBYo2XTMfBtEil","d6UeMJLKJMWqnBod01D9L3","d6s44hIEhLuqW4h0mg3OLC","d7qwaHOzlJ+LzrF3nA31OR","d7xaiivF1Jborv+UzKQwkE","d8fnGejhZDO5WR1dTsbDnK","d8qQLCkkRCrJ6TIi8ZxiJK","d89WnC76hOCL67YakKxYDs","d9arfuC1tA4511q7iCz92S","d9+Uz6hZRGnKR0oPXJl8li","d9+8fVSypIU5g89/NCI1S1","dahyExM5ZP6ofTcEc77DaF","damQzT2ABL77EAMag4IhS2","dbBiKuSWRFjrevgmcp9aC8","dbnKEc13BFnoYmjoOwKATt","dcB2iMDJpPuKpLGdgEKB3n","dcC5kQZdVPma7Tf6O5QPZZ","dcRI1/nklMEq0+6QKD0Cdk","dcVDle/iRPU69AkXgxXLfz","ddJ4mUAvxMYq8YQltxd+HA","ddODxboHpF6JxQsQc3eUuc","ddT6zMCLJHZJJIkQj1O9di","ddgrla4X1JF5iQGQmr4ijT","ddlfcS7CZAIZVwA8omSFHh","deGyLdslNL9pVibRQf/dvf","deKM4OhABHPIibiB8OdUTv","deTUSDrxtI/KbmvpcBHrVQ","deVjjhpONLiKlmym4vuBFW","dekf88lNBEE5aQxiAxCgus","dfrFgkE2tK6KqboaBXZrUT","dfwdzvIYRMqZuoQYyTKAbU","e0Dzz+MEVITIhgWMTfYgbv","e0S75dSb1AhYlyVFYgz6ey","e04l0S07BPlKMCrpgIWKGC","e1OoISNsRJxoiqqs1Jz5eF","e1fdZT9wRPPbC4uDDNLmw+","e1kaqQTyJPWaTcjfu9UkvI","e2LDbFlaFF8p3bnzyzsfF+","e2PS+rVC9O5pI/zTP6W+KM","e2a5b3gfZKTJV99VfpCx9I","e2lqgp00RDEZslfCahgfuH","e30SfxMk1H6rbMcsrbNnw9","e366N5FkJEN4avZkAaPYRM","e4Vq9y2SlPPYrvqi6wFm2e","e4lwZuv8BIp7KvCJBlLpzN","e5HzHPhexO8J74rA+eT3pW","e5v9CGo/NDoZa5BLg+yyxc","e579aPYV5OrZDygO1oJxyq","e6AzBzGj1NNZzVe1Oyi8Ib","e6Vlia/vBOy7ROE92d8mWK","e6gs1vTfZHdYApz7VJMxJm","e7ps2QrYJCO73Eo+0ZuxX4","e74Odei31ANb/XeyyAPax+","e8bFuc1tFOJIvUXyLsI+bN","e8sYbjhoRI/pHh54skV4IM","e8y3xw/7dLkLGRSwJ4iZVl","e9uh+J6kxM7JIv9Nl6fweZ","ea0XcCrKlOOqE0AmEDg/4J","ecV6ynRAtLIYF0zH7zJuw2","ecV/PjBhhOO6EK1GUG5wKD","ecZcN5n5pGoLzI9I2wQ++k","ecvp1ywSlEFKa6SwoPlMuG","ecxkEz2bVDjZJM4ZIABKiw","edPU1N3M9BpKftOj5jGIH6","edcyMS7BNK/JhyyPV5hl0e","ed6zpmVKhHEorzMMsfE8Ur","efA9HtehtH1KuEMXQNYA3z","f0QyxQejJBFoDvIw4/7X7t","f0hPxYrP9MxZWcz4pbr93Q","f0yYe9PvtP54we+8BBpKwq","f05EQWoP1MfocKwu0hcHwy","f1byniuONAIrKc/3L4FZVk","f1eEyzONNDeLkTTb/7ygL+","f1uQ/UJD1D0LMNncjbv0MV","f2EyZGn4BK2ppTLQhuZGke","f2Jvu19LBAkaRwjpVwKJSc","f2fbN8ZTtEva9RgSPD6bIa","f2l7BV2yBFD50sdycGxyJe","f2tvPa+NlIJa8ct/JVbH0o","f3G5xBGllIm5/LRFtU8g/+","f3rMWOXotKH4YAqKYLjy0B","f3v5bDdRFOBrUrj51v+H6u","f4AtzYI8pNKZ/oKWVNLysx","f4BW9wtGRIYa1ZFK3r8Prr","f4LS+nebZMDZc6EVyPaLQm","f4OppI3RBDEL7elZSBYS3k","f4TB3D4kBObY0oWRPVCElr","f4g+cFiLRPtqqSCcXwp4Rp","f5VIqr7mJFWoULzOjZDZKr","f5qc59UBZNxY0iEjsIhSXr","f55E4WmM9LP6Vva+g71sJL","f59u3PfkBMIIdtcLynvZA6","f6HQwPSSpA0b+5txRQtR1V","f6R4U0I0lP07Am7hrO9hWD","f6luAn5TZDxKXBRWNA9kWs","f64qAkXRhOtI2tjg3n4YW9","f7HPhtHaxDg4x4h8bNWgxk","f7aVGWhLhPz6T+MCdM+91y","f7ebQlB+ZFxYaMQKFIeTAc","f71sZD9PdPO5UuSJnlj+hd","f8rkq/9VRCSIUEjGbI4T/p","f8sPCmV3ZOeJh1oY7PFmbg","f9KRYfcWFD0bkVgS9tChIr","f9ObYNAfJBtqCbZsfWFcg8","f9Oiupx5FOMKoSkYYOTKkm","f9YmEa62JFU7qk5MqVDZ7o","f9Z6/+53JE+KfJvdr+V7mH","faA/cwmUlMvJYZnjdhOjIS","faVXSETPRHvLBgCN6a70u9","fa7MzX9W9N+aIcMlcrp0hA","fbQbwnB3xB8KB7KEmQMEss","fbTY7QQlBOzoKaN/IUlSzi","fblgQRIelMQK57scRr1gFs","fboUoruJlCYbwkofweKHk6","fb3OeQy11OfYTT5OAlfj37","fcCb8MnpNEUo71lqQFNAtG","fcTmBJHnVMo6rpGNPnqJhB","fcXhboCOdDX4eGaeXJ0dRX","fcc4hzi3VKr4xmFJvIxp5b","fcd7OtHdhCZrKRNiVSCTAp","fcjoXS+V5AuIDvOvcjElfH","fcqDVbgxxP/pgWTUZT+As9","fcykykzNpBkqaRY6DYl55U","fdbQBbDpNLsLumuK8/ZoJ4","fdlWDrjqdJ4IpSmhdHro2Y","fdndTBYFdP2omROurVVEsO","fdvBlLVahFPrUQr40EGiPc","feGFCOQqhHV5QAwWZta/R8","feOeXHNQxO7K7wpCt85VL0","feZaimMB5MvYfJVR13Tqvk","fefGpGRT1OAZqLhdPbwAbV","femP2ByARCaqOe+oAGt4Z5","fe/VfCEPNAFqTd91mjxUHs","ffiZxToXBMQqHgr2GVuCdE","ff623+0+ZJNYnyG/noCwW4"],"scenes":{},"redirect":[],"deps":[],"packs":{"08d9d8aaf":[1,2,3,4,5,6,7,8,9,10,11,14,15,16]},"name":"resources","importBase":"import","nativeBase":"native","debug":false,"isZip":false,"encrypted":false,"versions":{"import":[18,"0d1ff",19,"1761e",20,"007d9",21,"7d7a0",22,"5c565",23,"9e48a",24,"3ba10",25,"8525b",26,"552b6",27,"2640a",28,"3f643",29,"16497",30,"afbc2",31,"ad88a",32,"6df6f",33,"d4d31",34,"bb7e1",35,"facbc",36,"3eb73",37,"08788",38,"a464b",39,"2de00",40,"8a1a2",41,"478a9",42,"feb46",43,"6ad6e",44,"d10d3",45,"f8e14",46,"d9387",47,"b77f1","08d9d8aaf","1a978",48,"e8822",49,"735ff",50,"dd856",51,"6bc25",52,"a715c",53,"05f28",54,"4cde7",55,"b3318",56,"40ddb",57,"a93a2",58,"920bd",59,"a0341",60,"c063c",61,"2c3d9",62,"4d950",63,"555a1",64,"af16d",65,"6c619",66,"4374c",0,"77359",67,"9826b",68,"ec88f",69,"b2feb",70,"ea9db",71,"e6a7e",72,"36c2c",73,"02355",74,"08cd9",75,"4f5f6",76,"83ad9",77,"cb51c",78,"7fad7",79,"45318",80,"9e753",81,"0b0c2",82,"175a7",83,"3ad91",84,"73969",85,"3f9e2",86,"33dbb",87,"64add",88,"6b573",89,"c144f",90,"b7a8a",91,"1d10b",92,"47b78",93,"92fb9",94,"e2722",95,"f1ed0",96,"352e7",97,"e20cf",98,"48766",99,"131cc",100,"34471",101,"30844",102,"c7e70",103,"d2929",104,"51ad4",105,"97062",106,"ef420",107,"b836d",108,"39478",109,"2e042",110,"64fa7",111,"fb7ed",112,"5e14f",113,"15629",114,"0d7af",115,"b2675",116,"bc984",117,"ce053",118,"a359f",119,"42853",120,"285e4",121,"29dd8",122,"c9763",123,"106c9",124,"17490",125,"74683",126,"07c63",127,"f2649",128,"b6910",129,"c9f4a",130,"c2275",131,"2b4cd",132,"556ec",133,"5bdf7",134,"99cbc",135,"f46ba",136,"f156b",137,"53188",138,"be26e",139,"a4d99",140,"6ec9c",141,"456d7",142,"43f2f",143,"c54a5",144,"10fd2",145,"997a9",146,"c4cf1",147,"81274",148,"02541",149,"c118c",150,"d50f3",151,"6cea0",152,"5eef6",153,"a5adc",154,"c020f",155,"30c9c",156,"56e7b",157,"c18d2",158,"8f4af",159,"2a11f",160,"c9ca6",161,"71bb5",162,"5a2fa",163,"c1145",164,"d40ea",165,"c5520",166,"797b0",167,"63407",168,"fef11",169,"a3f8a",170,"aa637",171,"53c5f",172,"cddfd",173,"7da38",174,"147b3",175,"0da5b",176,"93b50",177,"ba947",178,"9017a",179,"73f33",180,"22ea9",181,"efd2b",182,"c31a1",183,"78803",184,"1f784",185,"b7a03",186,"2bdb1",187,"51e7a",188,"6484d",189,"c44e0",190,"c0582",191,"39b00",192,"6add0",193,"904c3",194,"c4498",195,"2bae7",196,"5f298",197,"dcb8f",198,"60d0c",199,"28d04",200,"134ec",201,"15e37",202,"179bf",203,"ba8c4",204,"0a030",205,"bfd6f",206,"6fb83",207,"73c7b",208,"8eced",209,"eae65",210,"dbf29",211,"f0026",212,"701d2",213,"32f3b",214,"69103",215,"f959b",216,"20730",217,"dab36",218,"663ac",219,"eecd0",220,"a0f8b",221,"62ee8",222,"84d38",223,"cf5bf",224,"3fd3e",225,"b211d",226,"9d836",227,"0a605",228,"4160f",229,"89d6f",230,"9338b",231,"cbb36",232,"21f44",233,"62066",234,"fc938",235,"192f3",236,"09872",237,"120f5",238,"cc0bd",239,"ae92f",240,"9d83b",241,"40ec6",242,"35755",243,"bbb2d",244,"44221",245,"57deb",246,"f1973",247,"8295d",248,"3bd02",249,"2c6a9",250,"af97f",251,"48fde",252,"f5706",253,"afb4c",254,"00fce",255,"b53c7",256,"536a9",257,"30e6d",258,"e4f53",259,"c4494",260,"e0d75",261,"cf4ae",262,"87d6c",263,"00f9a",264,"d0427",265,"9a2b2",266,"8045f",267,"92d61",268,"778be",269,"7ba9b",270,"11bb0",271,"00279",272,"ec567",273,"b6b31",274,"b2ef9",275,"44d95",276,"bad2d",277,"af20a",278,"194ea",279,"fd690",280,"ae91f",281,"5747a",282,"f9bad",283,"5d944",284,"e0fac",285,"a3de4",286,"49ed5",287,"301d3",288,"a4b27",289,"35470",290,"7b391",291,"aa096",292,"84b58",293,"e3a7b",294,"58b31",295,"ea1c5",296,"9c483",297,"35f6f",298,"a0ff6",299,"508e4",300,"498ed",301,"bde87",302,"8e481",303,"f8e18",304,"453d6",305,"2ae91",306,"7cd28",307,"4cc04",308,"15ed6",309,"ee77a",310,"1b3fc",311,"b1134",312,"f7855",313,"0ce7f",314,"35e26",315,"4c391",316,"885e8",317,"11acd",318,"437fb",319,"441c7",320,"7daa2",321,"0f10d",322,"fe2bc",323,"2fd90",324,"da36d",325,"44583",326,"af84d",327,"99830",328,"e9caa",329,"e0d43",330,"0536f",331,"10ad3",332,"ad93a",333,"3aad2",334,"55e2c",335,"0755a",336,"7a7d7",337,"42dc5",338,"0465d",339,"59b4d",340,"ef1d8",341,"0a680",342,"a2ed6",343,"e3c7c",344,"b244f",345,"7f617",346,"297cc",347,"8d9ef",348,"dc085",349,"cf7aa",350,"fa188",351,"3f80a",352,"ea23c",353,"b903f",354,"c8324",355,"fd333",356,"40b51",357,"608b3",358,"af785",359,"caa0b",360,"09c3d",361,"8f5ca",362,"9d646",363,"5a6b5",364,"5a822",365,"25bca",366,"f466f",367,"9ad52",368,"3bed6",369,"babc3",370,"93c18",371,"85385",372,"15256",373,"26925",374,"22435",375,"29077",376,"fc2b9",377,"5cac0",378,"3e2f2",379,"5de8f",380,"af602",381,"2000d",382,"7fd30",383,"58bd0",384,"6d712",385,"f7e84",386,"2e790",387,"6bddb",388,"1d862",389,"da33c",390,"0e604",391,"a467b",392,"d2659",393,"1da8e",394,"565a4",395,"71cbe",396,"fd0a6",397,"7f005",398,"3550b",399,"ec17e",400,"4a961",401,"d0dd3",402,"4f6f4",403,"ec666",404,"c14bd",405,"b3c4c",406,"5a652",407,"7d897",408,"c66ec",409,"2d863",410,"c06b1",411,"e766f",412,"0cf81",413,"bf150",414,"30e5b",415,"222f1",416,"99248",417,"b1cbc",418,"12d88",419,"3e198",420,"e773d",421,"14313",422,"46d6c",423,"3ad3c",424,"ea173",425,"d37b7",426,"33bf6",427,"f4f7c",428,"bf183",429,"09649",430,"f3036",431,"460c2",432,"60643",433,"85d20",434,"2ff9e",435,"83ea9",436,"fd811",437,"85c4d",438,"51ff8",439,"5d0e0",440,"7caf5",441,"056ea",442,"2ace1",443,"63fb4",444,"88ada",445,"c8826",446,"1654a",447,"feef2",448,"e7e4a",449,"b3f55",450,"0d1ef",451,"a21d4",452,"825fa",453,"42c40",454,"f26e3",455,"1897d",456,"4d04b",457,"62e8e",458,"7175c",459,"c8239",460,"25310",461,"d312d",462,"574af",463,"5b11a",464,"a6c5b",465,"09bae",466,"d25c6",467,"ea6cc",468,"80c75",469,"57123",470,"60eb1",471,"a7bf4",472,"2bf10",473,"dc534",474,"17262",475,"3f040",476,"b48ac",477,"a6db1",478,"94e0d",479,"a52d3",480,"018d9",481,"2bf03",482,"bf588",483,"74d57",484,"0269c",485,"d18b2",486,"6cd7f",487,"6e42a",488,"98c0b",489,"bba07",490,"50c23",491,"3be1e",492,"3a7a4",493,"1a57d",494,"02a2f",495,"5400e",496,"f7c61",497,"b5dab",498,"823d8",499,"bcb01",500,"7cac8",501,"9fb9d",502,"cb4e4",503,"70053",504,"151e5",505,"cd6c6",506,"e2361",507,"4b5c4",508,"9b75e",509,"373ec",510,"72204",511,"688e8",512,"50ee7",513,"08472",514,"78277",515,"1245f",516,"d739b",517,"77b44",518,"9898d",519,"aedb3",520,"a94f6",521,"5d74f",522,"e2126",523,"5e95e",524,"db639",525,"34c30",526,"96a0a",527,"c9186",528,"5abfc",529,"0b543",530,"d60fa",531,"34ff2",532,"bc1fa",533,"3b469",534,"44d1e",535,"c19e2",536,"96088",537,"6da12",538,"19326",539,"5c0b8",540,"478da",541,"eacf6",542,"46deb",543,"b6fc9",544,"b14d7",545,"b2164",546,"37e89",547,"7532b",548,"bb683",549,"ad832",550,"fb422",551,"3585e",552,"67266",553,"5ce68",554,"4b321",555,"948ff",556,"e6442",557,"b913a",558,"67738",559,"57a88",560,"13b00",561,"4da55",562,"903da",563,"5c205",564,"f0456",565,"69c03",566,"5887d",567,"f96f3",568,"bca6a",569,"d6500",570,"b9f67",571,"1b8fd",572,"d0a69",573,"c6be2",574,"7c95f",575,"878a8",576,"51ab4",577,"f8d22",578,"53c80",579,"98bf3",580,"1ebfb",581,"ae7c8",582,"2c58f",583,"88018",584,"431ea",585,"8fb5e",586,"347e7",587,"4b119",588,"ee0a5",589,"9d1aa",590,"ba7b4",591,"846a0",592,"949f1",593,"a5b2d",594,"295b8",595,"e86c8",596,"2890f",597,"40aac",598,"0401d",599,"e1258",600,"3b6a9",601,"2614a",602,"f6fd4",603,"c64f7",604,"70eab",605,"040b1",606,"71b43",607,"67ffb",608,"619d7",609,"04dd3",610,"0d85b",611,"3a189",612,"30c9f",613,"d36dd",614,"ea43c",615,"af05d",616,"7e136",617,"876d6",618,"f4949",619,"71406",620,"2c27c",621,"6315c",622,"4a025",623,"593d4",624,"84c0b",625,"2d679",626,"88c17",627,"6f7ed",628,"f9a07",629,"f095c",630,"199ec",631,"c9892",632,"033b7",633,"1d94c",634,"4812e",635,"23ecc",636,"a4a26",637,"4e94a",638,"3dab1",639,"adc19",640,"e4f34",641,"752e1",642,"e4498",643,"9a861",644,"28692",645,"3be3d",646,"79f7d",647,"f8310",648,"2314e",649,"ea344",650,"b3a8b",651,"f5b19",652,"0660a",653,"b2621",654,"9d639",655,"e4160",656,"cbbbe",657,"0a5df",658,"c5444",659,"49149",660,"1776d",661,"7f5be",662,"b5b8c",663,"64979",664,"72bbd",665,"6ec2d",666,"a6f57",667,"da72b",668,"ea9ee",669,"39e5c",670,"1232b",671,"7ff26",672,"b05ca",673,"f0b8c",674,"b443e",675,"8ba15",676,"c877f",677,"97be1",678,"6babb",679,"84931",680,"d28a6",681,"f4c0c",682,"58511",683,"22460",684,"48f6f",685,"8ca32",686,"e54aa",687,"9a57e",688,"d970a",689,"d42cb",690,"3a722",691,"db86e",692,"d4749",693,"e4bed",694,"82005",695,"fee46",696,"d2c74",697,"84400",698,"0fdbe",699,"33ca5",700,"20730",701,"76480",702,"182f0",703,"b1a1c",704,"e63f3",705,"ccc18",706,"dab4f",707,"526f9",708,"517bb",709,"0e036",710,"b4861",711,"29127",712,"029c8",713,"ccb57",714,"f1737",715,"ac8cc",716,"4247c",717,"d2b6a",718,"4a70f",719,"05b35",720,"79ddd",721,"b4069",722,"158a3",723,"4896c",724,"f1f08",725,"4bc45",726,"db9fd",727,"744ba",728,"6393c",729,"37e7d",730,"1e6fd",731,"3ec37",732,"89dd9",733,"ecf3c",734,"dee7f",735,"8210a",736,"767d3",737,"b4072",738,"68663",739,"9dd38",740,"bcbc0",741,"93cfc",742,"e3254",743,"b8de2",744,"f51a4",745,"d0f0f",746,"4f502",747,"da5d0",748,"76b27",749,"8b83d",750,"b0517",751,"dc777",752,"663f8",753,"d1b95",754,"36c2c",755,"2a432",756,"32a47",757,"01a35",758,"c00e6",759,"825b3",760,"aef39",761,"98c52",762,"dd36d",763,"54ec7",764,"6e8b9",765,"af95d",766,"87ce2",767,"81047",768,"7cea9",769,"1c645",770,"bb4b9",771,"0d56e",772,"b83a7",773,"5ec3c",774,"7c50c",775,"2a6e8",776,"8a3b8",777,"85426",778,"9e544",779,"eb5e7",780,"e1827",781,"4337b",782,"9e52b",783,"9c47e",784,"c404e",785,"c35f2",786,"2fc95",787,"626bd",788,"f05a2",789,"646d6",790,"94c58",791,"d87fe",792,"a4b00",793,"8cb74",794,"05351",795,"8d914",796,"cafd5",797,"e62db",798,"27c6a",799,"bcca4",800,"68ba6",801,"db718",802,"bbbc9",803,"3aec1",804,"8ba1e",805,"efca4",806,"1d13f",807,"33ec5",808,"5c9e5",809,"8e7a7",810,"45303",811,"753fc",812,"6f7fe",813,"e8653",814,"3152c",815,"69a49",816,"62b5f",817,"46cf4",818,"08895",819,"af673",820,"13c2d",821,"4e80e",822,"1c68e",823,"98f77",824,"1a525",825,"4f10a",826,"f1a63",827,"ad44d",828,"31212",829,"2e2f9",830,"74b1c",831,"ff159",832,"72199",833,"b522d",834,"a5ad9",835,"2bdb7",836,"1cc43",837,"a636b",838,"53150",839,"cfe2e",840,"fb6af",841,"bf26f",842,"edaad",843,"03754",844,"97cd2",845,"0b031",846,"c2ea5",847,"a3a3d",848,"81a56",849,"186d3",850,"19895",851,"4b173",852,"ad871",853,"26160",854,"9f5cb",855,"b6c09",856,"be73a",857,"53c2c",858,"ee36b",859,"8a0a4",860,"1f0d9",861,"8f4fd",862,"979f6",863,"2ef07",864,"fd02d",865,"e689d",866,"e5948",867,"d5d9b",12,"7dfcd",868,"63c16",869,"f3d20",870,"b2421",871,"9acdf",872,"ea9ec",873,"7b0cf",874,"136be",875,"08959",876,"21bb6",877,"e2c90",878,"a613d",879,"54773",880,"8c14f",881,"7ad4d",882,"d9ff5",883,"f48fd",884,"546c9",885,"727ad",886,"fc201",887,"15876",888,"a93e5",889,"6b038",890,"1d0c8",891,"dd6c5",892,"612f1",893,"3c687",894,"a845b",895,"2b33e",896,"3a654",897,"12902",898,"662cc",899,"5efd1",13,"71c1b",900,"ca0cb",901,"4e2f6",902,"1a59a",903,"b77e6",904,"8dfa7",905,"0aa9b",906,"262b0",907,"9362d",908,"307b1",909,"0ddf7",910,"3b932",911,"4f27d",912,"32988",913,"8fe51",914,"3805d",915,"1a38e",916,"1f457",917,"f868d",918,"7f1b8",919,"21e55",920,"07b6a",921,"95bb4",922,"f3dd2",923,"17401",924,"91393",925,"f3656",926,"9dcb6",927,"fff55",928,"fb6cb",929,"d5d6c",930,"9def5",931,"7accd",932,"29d5a",933,"5b292",934,"261d2",935,"6573e",936,"a7835",937,"bed06",938,"f7005",939,"a4641",940,"40842",941,"c1f92",942,"a4c53",943,"d17c6",944,"ef33b",945,"e8d48",946,"5724e",947,"c7e2a",948,"b681d",949,"7add3",950,"9888a",951,"423d2",952,"4ef21",953,"9f40e",954,"4cb99",955,"86d89",956,"c88ea",957,"54702",958,"f5c94",959,"e94a4",960,"e164a",961,"d0981",962,"9ab3e",963,"ca15f",964,"e4875",965,"5fe58",966,"f1f45",967,"0b1dc",968,"30811",969,"539f9",970,"5c84e",971,"1e6a3",972,"26e3f",973,"e9aeb",974,"c580b",975,"f7505",976,"01f84",977,"a455b",978,"237ef",979,"f2639",980,"e75ee",17,"1a0b3",981,"7b88c",982,"126e4",983,"a8ff0",984,"7c7c0",985,"5f14f",986,"7e831",987,"18fd8",988,"49725",989,"ba40c",990,"3fba3",991,"97da6",992,"043cf",993,"eab5c",994,"a11d4",995,"bc65e",996,"4c1f3",997,"f6e76",998,"ec408",999,"68232",1000,"447a0",1001,"97592",1002,"aace5",1003,"827b1",1004,"89e0e",1005,"5fd49",1006,"7d60d",1007,"f0ae6",1008,"73dbc",1009,"28191",1010,"38793",1011,"cee96",1012,"f1836",1013,"cf648",1014,"c0e1b",1015,"ecd82",1016,"3067c",1017,"0abe3",1018,"a7000",1019,"522a1",1020,"4354d",1021,"dffc1",1022,"b12b0",1023,"e17a7",1024,"6a232",1025,"c1cd1",1026,"e9019",1027,"24d21",1028,"34345",1029,"94f44",1030,"12296",1031,"9493d"],"native":[0,"3a846",1,"70480",2,"502f3",3,"ede79",4,"19db1",5,"2b3b9",6,"228db",7,"8bd34",8,"c5a83",9,"02d0a",10,"9f596",11,"0671c",12,"9d5c7",13,"d3d8f",14,"cae64",15,"f8c04",16,"aa4bf",17,"05b18"]}}